Workbook

Sheet MAIO26
B1: Data: 04/05/2026
A2: SABORES | B2: Estoque Inicial | C2: Furou | D2: Fez | E2: Quantidade de Geladinhos | F2: Voltaram | G2: Vendidos | H2: Estoque Final | I2: R$
A3: Abacate | B3: =ABRIL26!H490 -> 35 | E3: 6 | F3: 6 | G3: =E3-F3 -> 0 | H3: =B3-C3+D3-G3 -> 35 | I3: =G3*6 -> 0
A4: Abacaxi | B4: =ABRIL26!H491 -> 28 | E4: 3 | F4: 3 | G4: =E4-F4 -> 0 | H4: =B4-C4+D4-G4 -> 28 | I4: =G4*6 -> 0
A5: Açaí | B5: =ABRIL26!H492 -> 17 | E5: 5 | F5: 4 | G5: =E5-F5 -> 1 | H5: =B5-C5+D5-G5 -> 16 | I5: =G5*6 -> 6
A6: Amendoim | B6: =ABRIL26!H493 -> 32 | E6: 6 | F6: 5 | G6: =E6-F6 -> 1 | H6: =B6-C6+D6-G6 -> 31 | I6: =G6*6 -> 6
A7: Brigadeiro | B7: =ABRIL26!H494 -> 24 | E7: 4 | F7: 3 | G7: =E7-F7 -> 1 | H7: =B7-C7+D7-G7 -> 23 | I7: =G7*6 -> 6
A8: Buriti | B8: =ABRIL26!H495 -> 32 | E8: 6 | F8: 2 | G8: =E8-F8 -> 4 | H8: =B8-C8+D8-G8 -> 28 | I8: =G8*6 -> 24
A9: Coco | B9: =ABRIL26!H496 -> 15 | D9: 30 | E9: 5 | F9: 4 | G9: =E9-F9 -> 1 | H9: =B9-C9+D9-G9 -> 44 | I9: =G9*6 -> 6
A10: Coco Queimado | B10: =ABRIL26!H497 -> 15 | E10: 4 | F10: 3 | G10: =E10-F10 -> 1 | H10: =B10-C10+D10-G10 -> 14 | I10: =G10*6 -> 6
A11: Cupuaçu | B11: =ABRIL26!H498 -> 19 | E11: 5 | F11: 4 | G11: =E11-F11 -> 1 | H11: =B11-C11+D11-G11 -> 18 | I11: =G11*6 -> 6
A12: Maracujá | B12: =ABRIL26!H499 -> 22 | E12: 5 | F12: 5 | G12: =E12-F12 -> 0 | H12: =B12-C12+D12-G12 -> 22 | I12: =G12*6 -> 0
A13: Maracujá com nutella | B13: =ABRIL26!H500 -> 35 | E13: 5 | F13: 5 | G13: =E13-F13 -> 0 | H13: =B13-C13+D13-G13 -> 35 | I13: =G13*6 -> 0
A14: Milho verde | B14: =ABRIL26!H501 -> 8 | E14: 2 | F14: 1 | G14: =E14-F14 -> 1 | H14: =B14-C14+D14-G14 -> 7 | I14: =G14*6 -> 6
A15: Morango | B15: =ABRIL26!H502 -> 34 | C15: 1 | E15: 5 | F15: 4 | G15: =E15-F15 -> 1 | H15: =B15-C15+D15-G15 -> 32 | I15: =G15*6 -> 6
A16: Morango com Nutella | B16: =ABRIL26!H503 -> 32 | E16: 6 | F16: 5 | G16: =E16-F16 -> 1 | H16: =B16-C16+D16-G16 -> 31 | I16: =G16*6 -> 6
A17: Mousse de limão | B17: =ABRIL26!H504 -> 24 | E17: 3 | F17: 3 | G17: =E17-F17 -> 0 | H17: =B17-C17+D17-G17 -> 24 | I17: =G17*6 -> 0
A18: Ninho com Nutella | B18: =ABRIL26!H505 -> 25 | E18: 8 | F18: 2 | G18: =E18-F18 -> 6 | H18: =B18-C18+D18-G18 -> 19 | I18: =G18*6 -> 36
A19: Ninho com Morango | B19: =ABRIL26!H506 -> 17 | E19: 4 | F19: 2 | G19: =E19-F19 -> 2 | H19: =B19-C19+D19-G19 -> 15 | I19: =G19*6 -> 12
A20: Oreo | B20: =ABRIL26!H507 -> 17 | E20: 3 | F20: 2 | G20: =E20-F20 -> 1 | H20: =B20-C20+D20-G20 -> 16 | I20: =G20*6 -> 6
A21: Prestígio | B21: =ABRIL26!H508 -> 20 | E21: 8 | F21: 7 | G21: =E21-F21 -> 1 | H21: =B21-C21+D21-G21 -> 19 | I21: =G21*6 -> 6
A22: Pudim | B22: =ABRIL26!H509 -> 158 | E22: 25 | F22: 13 | G22: =E22-F22 -> 12 | H22: =B22-C22+D22-G22 -> 146 | I22: =G22*6 -> 72
A23: Uva | B23: =ABRIL26!H510 -> 6 | E23: 2 | F23: 2 | G23: =E23-F23 -> 0 | H23: =B23-C23+D23-G23 -> 6 | I23: =G23*6 -> 0
A24: Zero lactose coco | B24: =ABRIL26!H511 -> 12 | E24: 2 | F24: 0 | G24: =E24-F24 -> 2 | H24: =B24-C24+D24-G24 -> 10 | I24: =G24*6 -> 12
A25: Zero lactose morango | B25: =ABRIL26!H512 -> 16 | E25: 2 | F25: 2 | G25: =E25-F25 -> 0 | H25: =B25-C25+D25-G25 -> 16 | I25: =G25*6 -> 0
A26: TOTAL | B26: =SUM(B3:B25) -> 643 | C26: =SUM(C3:C25) -> 1 | D26: =SUM(D3:D25) -> 30 | E26: =SUM(E3:E25) -> 124 | F26: =SUM(F3:F25) -> 87 | G26: =SUM(G3:G25) -> 37 | H26: =SUM(H3:H25) -> 635 | I26: =SUM(I3:I25) -> 222
F27: Saldo
B29: Data: 05/05/2026
A30: SABORES | B30: Estoque Inicial | C30: Furou | D30: Fez | E30: Quantidade de Geladinhos | F30: Voltaram | G30: Vendidos | H30: Estoque Final | I30: R$
A31: Abacate | B31: =H3 -> 35 | E31: 6 | F31: 5 | G31: =E31-F31 -> 1 | H31: =B31-C31+D31-G31 -> 34 | I31: =G31*6 -> 6
A32: Abacaxi | B32: =H4 -> 28 | E32: 3 | F32: 3 | G32: =E32-F32 -> 0 | H32: =B32-C32+D32-G32 -> 28 | I32: =G32*6 -> 0
A33: Açaí | B33: =H5 -> 16 | E33: 5 | F33: 3 | G33: =E33-F33 -> 2 | H33: =B33-C33+D33-G33 -> 14 | I33: =G33*6 -> 12
A34: Amendoim | B34: =H6 -> 31 | E34: 6 | F34: 3 | G34: =E34-F34 -> 3 | H34: =B34-C34+D34-G34 -> 28 | I34: =G34*6 -> 18
A35: Brigadeiro | B35: =H7 -> 23 | E35: 4 | F35: 1 | G35: =E35-F35 -> 3 | H35: =B35-C35+D35-G35 -> 20 | I35: =G35*6 -> 18
A36: Buriti | B36: =H8 -> 28 | E36: 5 | F36: 4 | G36: =E36-F36 -> 1 | H36: =B36-C36+D36-G36 -> 27 | I36: =G36*6 -> 6
A37: Coco | B37: =H9 -> 44 | E37: 5 | F37: 4 | G37: =E37-F37 -> 1 | H37: =B37-C37+D37-G37 -> 43 | I37: =G37*6 -> 6
A38: Coco Queimado | B38: =H10 -> 14 | E38: 4 | F38: 2 | G38: =E38-F38 -> 2 | H38: =B38-C38+D38-G38 -> 12 | I38: =G38*6 -> 12
A39: Cupuaçu | B39: =H11 -> 18 | E39: 5 | F39: 4 | G39: =E39-F39 -> 1 | H39: =B39-C39+D39-G39 -> 17 | I39: =G39*6 -> 6
A40: Maracujá | B40: =H12 -> 22 | E40: 5 | F40: 3 | G40: =E40-F40 -> 2 | H40: =B40-C40+D40-G40 -> 20 | I40: =G40*6 -> 12
A41: Maracujá com nutella | B41: =H13 -> 35 | E41: 5 | F41: 3 | G41: =E41-F41 -> 2 | H41: =B41-C41+D41-G41 -> 33 | I41: =G41*6 -> 12
A42: Milho verde | B42: =H14 -> 7 | E42: 2 | F42: 1 | G42: =E42-F42 -> 1 | H42: =B42-C42+D42-G42 -> 6 | I42: =G42*6 -> 6
... A53: Zero lactose morango | B53: =H25 -> 16 | E53: 2 | F53: 2 | G53: =E53-F53 -> 0 | H53: =B53-C53+D53-G53 -> 16 | I53: =G53*6 -> 0
A54: TOTAL | B54: =SUM(B31:B53) -> 635 | C54: =SUM(C31:C53) -> 0 | D54: =SUM(D31:D53) -> 0 | E54: =SUM(E31:E53) -> 123 | F54: =SUM(F31:F53) -> 79 | G54: =SUM(G31:G53) -> 44 | H54: =SUM(H31:H53) -> 591 | I54: =SUM(I31:I53) -> 264
F55: Saldo
B57: Data: 06/05/2026
A58: SABORES | B58: Estoque Inicial | C58: Furou | D58: Fez | E58: Quantidade de Geladinhos | F58: Voltaram | G58: Vendidos | H58: Estoque Final | I58: R$
A59: Abacate | B59: =H31 -> 34 | G59: =E59-F59 -> 0 | H59: =B59-C59+D59-G59 -> 34 | I59: =G59*6 -> 0
A60: Abacaxi | B60: =H32 -> 28 | G60: =E60-F60 -> 0 | H60: =B60-C60+D60-G60 -> 28 | I60: =G60*6 -> 0
A61: Açaí | B61: =H33 -> 14 | G61: =E61-F61 -> 0 | H61: =B61-C61+D61-G61 -> 14 | I61: =G61*6 -> 0
A62: Amendoim | B62: =H34 -> 28 | G62: =E62-F62 -> 0 | H62: =B62-C62+D62-G62 -> 28 | I62: =G62*6 -> 0
A63: Brigadeiro | B63: =H35 -> 20 | G63: =E63-F63 -> 0 | H63: =B63-C63+D63-G63 -> 20 | I63: =G63*6 -> 0
A64: Buriti | B64: =H36 -> 27 | G64: =E64-F64 -> 0 | H64: =B64-C64+D64-G64 -> 27 | I64: =G64*6 -> 0
A65: Coco | B65: =H37 -> 43 | G65: =E65-F65 -> 0 | H65: =B65-C65+D65-G65 -> 43 | I65: =G65*6 -> 0
A66: Coco Queimado | B66: =H38 -> 12 | G66: =E66-F66 -> 0 | H66: =B66-C66+D66-G66 -> 12 | I66: =G66*6 -> 0
A67: Cupuaçu | B67: =H39 -> 17 | G67: =E67-F67 -> 0 | H67: =B67-C67+D67-G67 -> 17 | I67: =G67*6 -> 0
A68: Maracujá | B68: =H40 -> 20 | G68: =E68-F68 -> 0 | H68: =B68-C68+D68-G68 -> 20 | I68: =G68*6 -> 0
A69: Maracujá com nutella | B69: =H41 -> 33 | G69: =E69-F69 -> 0 | H69: =B69-C69+D69-G69 -> 33 | I69: =G69*6 -> 0
A70: Milho verde | B70: =H42 -> 6 | G70: =E70-F70 -> 0 | H70: =B70-C70+D70-G70 -> 6 | I70: =G70*6 -> 0
... A81: Zero lactose morango | B81: =H53 -> 16 | G81: =E81-F81 -> 0 | H81: =B81-C81+D81-G81 -> 16 | I81: =G81*6 -> 0
A82: TOTAL | B82: =SUM(B59:B81) -> 591 | C82: =SUM(C59:C81) -> 0 | D82: =SUM(D59:D81) -> 0 | E82: =SUM(E59:E81) -> 0 | F82: =SUM(F59:F81) -> 0 | G82: =SUM(G59:G81) -> 0 | H82: =SUM(H59:H81) -> 591 | I82: =SUM(I59:I81) -> 0
F83: Saldo
B85: Data: 07/05/2026
A86: SABORES | B86: Estoque Inicial | C86: Furou | D86: Fez | E86: Quantidade de Geladinhos | F86: Voltaram | G86: Vendidos | H86: Estoque Final | I86: R$
A87: Abacate | B87: =H59 -> 34 | G87: =E87-F87 -> 0 | H87: =B87-C87+D87-G87 -> 34 | I87: =G87*6 -> 0
A88: Abacaxi | B88: =H60 -> 28 | G88: =E88-F88 -> 0 | H88: =B88-C88+D88-G88 -> 28 | I88: =G88*6 -> 0
A89: Açaí | B89: =H61 -> 14 | G89: =E89-F89 -> 0 | H89: =B89-C89+D89-G89 -> 14 | I89: =G89*6 -> 0
A90: Amendoim | B90: =H62 -> 28 | G90: =E90-F90 -> 0 | H90: =B90-C90+D90-G90 -> 28 | I90: =G90*6 -> 0
A91: Brigadeiro | B91: =H63 -> 20 | G91: =E91-F91 -> 0 | H91: =B91-C91+D91-G91 -> 20 | I91: =G91*6 -> 0
A92: Buriti | B92: =H64 -> 27 | G92: =E92-F92 -> 0 | H92: =B92-C92+D92-G92 -> 27 | I92: =G92*6 -> 0
A93: Coco | B93: =H65 -> 43 | G93: =E93-F93 -> 0 | H93: =B93-C93+D93-G93 -> 43 | I93: =G93*6 -> 0
A94: Coco Queimado | B94: =H66 -> 12 | G94: =E94-F94 -> 0 | H94: =B94-C94+D94-G94 -> 12 | I94: =G94*6 -> 0
A95: Cupuaçu | B95: =H67 -> 17 | G95: =E95-F95 -> 0 | H95: =B95-C95+D95-G95 -> 17 | I95: =G95*6 -> 0
A96: Maracujá | B96: =H68 -> 20 | G96: =E96-F96 -> 0 | H96: =B96-C96+D96-G96 -> 20 | I96: =G96*6 -> 0
A97: Maracujá com nutella | B97: =H69 -> 33 | G97: =E97-F97 -> 0 | H97: =B97-C97+D97-G97 -> 33 | I97: =G97*6 -> 0
A98: Milho verde | B98: =H70 -> 6 | G98: =E98-F98 -> 0 | H98: =B98-C98+D98-G98 -> 6 | I98: =G98*6 -> 0
... A109: Zero lactose morango | B109: =H81 -> 16 | G109: =E109-F109 -> 0 | H109: =B109-C109+D109-G109 -> 16 | I109: =G109*6 -> 0
A110: TOTAL | B110: =SUM(B87:B109) -> 591 | C110: =SUM(C87:C109) -> 0 | D110: =SUM(D87:D109) -> 0 | E110: =SUM(E87:E109) -> 0 | F110: =SUM(F87:F109) -> 0 | G110: =SUM(G87:G109) -> 0 | H110: =SUM(H87:H109) -> 591 | I110: =SUM(I87:I109) -> 0
F111: Saldo
B113: Data: 08/05/2026
A114: SABORES | B114: Estoque Inicial | C114: Furou | D114: Fez | E114: Quantidade de Geladinhos | F114: Voltaram | G114: Vendidos | H114: Estoque Final | I114: R$
A115: Abacate | B115: =H87 -> 34 | G115: =E115-F115 -> 0 | H115: =B115-C115+D115-G115 -> 34 | I115: =G115*6 -> 0
A116: Abacaxi | B116: =H88 -> 28 | G116: =E116-F116 -> 0 | H116: =B116-C116+D116-G116 -> 28 | I116: =G116*6 -> 0
A117: Açaí | B117: =H89 -> 14 | G117: =E117-F117 -> 0 | H117: =B117-C117+D117-G117 -> 14 | I117: =G117*6 -> 0
A118: Amendoim | B118: =H90 -> 28 | G118: =E118-F118 -> 0 | H118: =B118-C118+D118-G118 -> 28 | I118: =G118*6 -> 0
A119: Brigadeiro | B119: =H91 -> 20 | G119: =E119-F119 -> 0 | H119: =B119-C119+D119-G119 -> 20 | I119: =G119*6 -> 0
A120: Buriti | B120: =H92 -> 27 | G120: =E120-F120 -> 0 | H120: =B120-C120+D120-G120 -> 27 | I120: =G120*6 -> 0
A121: Coco | B121: =H93 -> 43 | G121: =E121-F121 -> 0 | H121: =B121-C121+D121-G121 -> 43 | I121: =G121*6 -> 0
A122: Coco Queimado | B122: =H94 -> 12 | G122: =E122-F122 -> 0 | H122: =B122-C122+D122-G122 -> 12 | I122: =G122*6 -> 0
A123: Cupuaçu | B123: =H95 -> 17 | G123: =E123-F123 -> 0 | H123: =B123-C123+D123-G123 -> 17 | I123: =G123*6 -> 0
A124: Maracujá | B124: =H96 -> 20 | G124: =E124-F124 -> 0 | H124: =B124-C124+D124-G124 -> 20 | I124: =G124*6 -> 0
A125: Maracujá com nutella | B125: =H97 -> 33 | G125: =E125-F125 -> 0 | H125: =B125-C125+D125-G125 -> 33 | I125: =G125*6 -> 0
A126: Milho verde | B126: =H98 -> 6 | G126: =E126-F126 -> 0 | H126: =B126-C126+D126-G126 -> 6 | I126: =G126*6 -> 0
... A137: Zero lactose morango | B137: =H109 -> 16 | G137: =E137-F137 -> 0 | H137: =B137-C137+D137-G137 -> 16 | I137: =G137*6 -> 0
A138: TOTAL | B138: =SUM(B115:B137) -> 591 | C138: =SUM(C115:C137) -> 0 | D138: =SUM(D115:D137) -> 0 | E138: =SUM(E115:E137) -> 0 | F138: =SUM(F115:F137) -> 0 | G138: =SUM(G115:G137) -> 0 | H138: =SUM(H115:H137) -> 591 | I138: =SUM(I115:I137) -> 0
F139: Saldo
B141: Data: 11/05/2026
A142: SABORES | B142: Estoque Inicial | C142: Furou | D142: Fez | E142: Quantidade de Geladinhos | F142: Voltaram | G142: Vendidos | H142: Estoque Final | I142: R$
A143: Abacate | B143: =H115 -> 34 | G143: =E143-F143 -> 0 | H143: =B143-C143+D143-G143 -> 34 | I143: =G143*6 -> 0
A144: Abacaxi | B144: =H116 -> 28 | G144: =E144-F144 -> 0 | H144: =B144-C144+D144-G144 -> 28 | I144: =G144*6 -> 0
A145: Açaí | B145: =H117 -> 14 | G145: =E145-F145 -> 0 | H145: =B145-C145+D145-G145 -> 14 | I145: =G145*6 -> 0
...

Sheet ABRIL26
B1: Data: 01/04/2026
A2: SABORES | B2: Estoque Inicial | C2: Furou | D2: Fez | E2: Quantidade de Geladinhos | F2: Voltaram | G2: Vendidos | H2: Estoque Final | I2: R$
A3: Abacate | B3: =MARÇO26!H576 -> 36 | C3: 1 | E3: 6 | F3: 0 | G3: =E3-F3 -> 6 | H3: =B3-C3+D3-G3 -> 29 | I3: =G3*6 -> 36
A4: Abacaxi | B4: =MARÇO26!H577 -> 27 | C4: 2 | E4: 4 | F4: 1 | G4: =E4-F4 -> 3 | H4: =B4-C4+D4-G4 -> 22 | I4: =G4*6 -> 18
A5: Açaí | B5: =MARÇO26!H578 -> 26 | E5: 6 | F5: 2 | G5: =E5-F5 -> 4 | H5: =B5-C5+D5-G5 -> 22 | I5: =G5*6 -> 24
A6: Amendoim | B6: =MARÇO26!H579 -> 33 | C6: 1 | E6: 8 | F6: 2 | G6: =E6-F6 -> 6 | H6: =B6-C6+D6-G6 -> 26 | I6: =G6*6 -> 36
A7: Brigadeiro | B7: =MARÇO26!H580 -> 23 | C7: 1 | E7: 4 | F7: 0 | G7: =E7-F7 -> 4 | H7: =B7-C7+D7-G7 -> 18 | I7: =G7*6 -> 24
A8: Buriti | B8: =MARÇO26!H581 -> 13 | E8: 8 | F8: 2 | G8: =E8-F8 -> 6 | H8: =B8-C8+D8-G8 -> 7 | I8: =G8*6 -> 36
A9: Coco | B9: =MARÇO26!H582 -> 18 | E9: 4 | F9: 2 | G9: =E9-F9 -> 2 | H9: =B9-C9+D9-G9 -> 16 | I9: =G9*6 -> 12
A10: Coco Queimado | B10: =MARÇO26!H583 -> 10 | E10: 4 | F10: 3 | G10: =E10-F10 -> 1 | H10: =B10-C10+D10-G10 -> 9 | I10: =G10*6 -> 6
A11: Cupuaçu | B11: =MARÇO26!H584 -> 27 | E11: 6 | F11: 2 | G11: =E11-F11 -> 4 | H11: =B11-C11+D11-G11 -> 23 | I11: =G11*6 -> 24
A12: Maracujá | B12: =MARÇO26!H585 -> 28 | E12: 6 | F12: 6 | G12: =E12-F12 -> 0 | H12: =B12-C12+D12-G12 -> 28 | I12: =G12*6 -> 0
A13: Maracujá com nutella | B13: =MARÇO26!H586 -> 13 | E13: 8 | F13: 4 | G13: =E13-F13 -> 4 | H13: =B13-C13+D13-G13 -> 9 | I13: =G13*6 -> 24
A14: Milho verde | B14: =MARÇO26!H587 -> 5 | E14: 3 | F14: 0 | G14: =E14-F14 -> 3 | H14: =B14-C14+D14-G14 -> 2 | I14: =G14*6 -> 18
A15: Morango | B15: =MARÇO26!H588 -> 7 | D15: 24 | E15: 2 | F15: 0 | G15: =E15-F15 -> 2 | H15: =B15-C15+D15-G15 -> 29 | I15: =G15*6 -> 12
A16: Morango com Nutella | B16: =MARÇO26!H589 -> 36 | C16: 1 | E16: 12 | F16: 1 | G16: =E16-F16 -> 11 | H16: =B16-C16+D16-G16 -> 24 | I16: =G16*6 -> 66
A17: Mousse de limão | B17: =MARÇO26!H590 -> 16 | E17: 4 | F17: 2 | G17: =E17-F17 -> 2 | H17: =B17-C17+D17-G17 -> 14 | I17: =G17*6 -> 12
A18: Ninho com Nutella | B18: =MARÇO26!H591 -> 33 | C18: 1 | E18: 18 | F18: 3 | G18: =E18-F18 -> 15 | H18: =B18-C18+D18-G18 -> 17 | I18: =G18*6 -> 90
A19: Ninho com Morango | B19: =MARÇO26!H592 -> 15 | C19: 1 | E19: 6 | F19: 5 | G19: =E19-F19 -> 1 | H19: =B19-C19+D19-G19 -> 13 | I19: =G19*6 -> 6
A20: Oreo | B20: =MARÇO26!H593 -> 17 | E20: 5 | F20: 1 | G20: =E20-F20 -> 4 | H20: =B20-C20+D20-G20 -> 13 | I20: =G20*6 -> 24
A21: Prestígio | B21: =MARÇO26!H594 -> 44 | C21: 4 | E21: 8 | F21: 4 | G21: =E21-F21 -> 4 | H21: =B21-C21+D21-G21 -> 36 | I21: =G21*6 -> 24
A22: Pudim | B22: =MARÇO26!H595 -> 48 | C22: 3 | D22: 34 | E22: 52 | F22: 11 | G22: =E22-F22 -> 41 | H22: =B22-C22+D22-G22 -> 38 | I22: =G22*6 -> 246
A23: Uva | B23: =MARÇO26!H596 -> 14 | C23: 1 | E23: 3 | F23: 2 | G23: =E23-F23 -> 1 | H23: =B23-C23+D23-G23 -> 12 | I23: =G23*6 -> 6
A24: Zero lactose coco | B24: =MARÇO26!H597 -> 20 | E24: 5 | F24: 3 | G24: =E24-F24 -> 2 | H24: =B24-C24+D24-G24 -> 18 | I24: =G24*6 -> 12
A25: Zero lactose morango | B25: =MARÇO26!H598 -> 19 | E25: 3 | F25: 3 | G25: =E25-F25 -> 0 | H25: =B25-C25+D25-G25 -> 19 | I25: =G25*6 -> 0
A26: TOTAL | B26: =SUM(B3:B25) -> 528 | E26: =SUM(E2:E25) -> 185 | F26: =SUM(F2:F25) -> 59 | G26: =SUM(G2:G25) -> 126 | H26: =SUM(H3:H25) -> 444 | I26: =SUM(I2:I25) -> 756
F27: Saldo
B29: Data: 06/04/2026
A30: SABORES | B30: Estoque Inicial | C30: Furou | D30: Fez | E30: Quantidade de Geladinhos | F30: Voltaram | G30: Vendidos | H30: Estoque Final | I30: R$
A31: Abacate | B31: =H3 -> 29 | E31: 6 | F31: 0 | G31: =E31-F31 -> 6 | H31: =B31-C31+D31-G31 -> 23 | I31: =G31*6 -> 36
A32: Abacaxi | B32: =H4 -> 22 | E32: 3 | F32: 2 | G32: =E32-F32 -> 1 | H32: =B32-C32+D32-G32 -> 21 | I32: =G32*6 -> 6
A33: Açaí | B33: =H5 -> 22 | E33: 5 | F33: 4 | G33: =E33-F33 -> 1 | H33: =B33-C33+D33-G33 -> 21 | I33: =G33*6 -> 6
A34: Amendoim | B34: =H6 -> 26 | E34: 6 | F34: 5 | G34: =E34-F34 -> 1 | H34: =B34-C34+D34-G34 -> 25 | I34: =G34*6 -> 6
A35: Brigadeiro | B35: =H7 -> 18 | E35: 4 | F35: 0 | G35: =E35-F35 -> 4 | H35: =B35-C35+D35-G35 -> 14 | I35: =G35*6 -> 24
A36: Buriti | B36: =H8 -> 7 | E36: 5 | F36: 4 | G36: =E36-F36 -> 1 | H36: =B36-C36+D36-G36 -> 6 | I36: =G36*6 -> 6
A37: Coco | B37: =H9 -> 16 | E37: 4 | F37: 3 | G37: =E37-F37 -> 1 | H37: =B37-C37+D37-G37 -> 15 | I37: =G37*6 -> 6
A38: Coco Queimado | B38: =H10 -> 9 | E38: 3 | F38: 2 | G38: =E38-F38 -> 1 | H38: =B38-C38+D38-G38 -> 8 | I38: =G38*6 -> 6
A39: Cupuaçu | B39: =H11 -> 23 | E39: 5 | F39: 2 | G39: =E39-F39 -> 3 | H39: =B39-C39+D39-G39 -> 20 | I39: =G39*6 -> 18
A40: Maracujá | B40: =H12 -> 28 | E40: 5 | F40: 4 | G40: =E40-F40 -> 1 | H40: =B40-C40+D40-G40 -> 27 | I40: =G40*6 -> 6
A41: Maracujá com nutella | B41: =H13 -> 9 | E41: 5 | F41: 4 | G41: =E41-F41 -> 1 | H41: =B41-C41+D41-G41 -> 8 | I41: =G41*6 -> 6
A42: Milho verde | B42: =H14 -> 2 | E42: 2 | F42: 2 | G42: =E42-F42 -> 0 | H42: =B42-C42+D42-G42 -> 2 | I42: =G42*6 -> 0
... A45: Mousse de limão | B45: =H17 -> 14 | E45: 3 | F45: 3 | G45: =E45-F45 -> 0 | H45: =B45-C45+D45-G45 -> 14 | I45: =G45*6 -> 0
A46: Ninho com Nutella | B46: =H18 -> 17 | C46: 1 | D46: 30 | E46: 8 | F46: 3 | G46: =E46-F46 -> 5 | H46: =B46-C46+D46-G46 -> 41 | I46: =G46*6 -> 30
A47: Ninho com Morango | B47: =H19 -> 13 | E47: 4 | F47: 4 | G47: =E47-F47 -> 0 | H47: =B47-C47+D47-G47 -> 13 | I47: =G47*6 -> 0
A48: Oreo | B48: =H20 -> 13 | E48: 3 | F48: 1 | G48: =E48-F48 -> 2 | H48: =B48-C48+D48-G48 -> 11 | I48: =G48*6 -> 12
A49: Prestígio | B49: =H21 -> 36 | E49: 6 | F49: 4 | G49: =E49-F49 -> 2 | H49: =B49-C49+D49-G49 -> 34 | I49: =G49*6 -> 12
A50: Pudim | B50: =H22 -> 38 | D50: 33 | E50: 25 | F50: 17 | G50: =E50-F50 -> 8 | H50: =B50-C50+D50-G50 -> 63 | I50: =G50*6 -> 48
A51: Uva | B51: =H23 -> 12 | E51: 2 | F51: 2 | G51: =E51-F51 -> 0 | H51: =B51-C51+D51-G51 -> 12 | I51: =G51*6 -> 0
A52: Zero lactose coco | B52: =H24 -> 18 | E52: 2 | F52: 0 | G52: =E52-F52 -> 2 | H52: =B52-C52+D52-G52 -> 16 | I52: =G52*6 -> 12
A53: Zero lactose morango | B53: =H25 -> 19 | E53: 2 | F53: 1 | G53: =E53-F53 -> 1 | H53: =B53-C53+D53-G53 -> 18 | I53: =G53*6 -> 6
A54: TOTAL | B54: =SUM(B31:B53) -> 444 | E54: =SUM(E30:E53) -> 118 | F54: =SUM(F30:F53) -> 72 | G54: =SUM(G30:G53) -> 46 | H54: =SUM(H31:H53) -> 460 | I54: =SUM(I30:I53) -> 276
F55: Saldo
B57: Data: 07/04/2026
A58: SABORES | B58: Estoque Inicial | C58: Furou | D58: Fez | E58: Quantidade de Geladinhos | F58: Voltaram | G58: Vendidos | H58: Estoque Final | I58: R$
A59: Abacate | B59: =H31 -> 23 | E59: 6 | F59: 6 | G59: =E59-F59 -> 0 | H59: =B59-C59+D59-G59 -> 23 | I59: =G59*6 -> 0
A60: Abacaxi | B60: =H32 -> 21 | E60: 3 | F60: 2 | G60: =E60-F60 -> 1 | H60: =B60-C60+D60-G60 -> 20 | I60: =G60*6 -> 6
A61: Açaí | B61: =H33 -> 21 | E61: 5 | F61: 5 | G61: =E61-F61 -> 0 | H61: =B61-C61+D61-G61 -> 21 | I61: =G61*6 -> 0
A62: Amendoim | B62: =H34 -> 25 | E62: 6 | F62: 3 | G62: =E62-F62 -> 3 | H62: =B62-C62+D62-G62 -> 22 | I62: =G62*6 -> 18
A63: Brigadeiro | B63: =H35 -> 14 | E63: 4 | F63: 4 | G63: =E63-F63 -> 0 | H63: =B63-C63+D63-G63 -> 14 | I63: =G63*6 -> 0
A64: Buriti | B64: =H36 -> 6 | D64: 35 | E64: 7 | F64: 6 | G64: =E64-F64 -> 1 | H64: =B64-C64+D64-G64 -> 40 | I64: =G64*6 -> 6
A65: Coco | B65: =H37 -> 15 | E65: 4 | F65: 1 | G65: =E65-F65 -> 3 | H65: =B65-C65+D65-G65 -> 12 | I65: =G65*6 -> 18
A66: Coco Queimado | B66: =H38 -> 8 | E66: 3 | F66: 3 | G66: =E66-F66 -> 0 | H66: =B66-C66+D66-G66 -> 8 | I66: =G66*6 -> 0
A67: Cupuaçu | B67: =H39 -> 20 | E67: 5 | F67: 3 | G67: =E67-F67 -> 2 | H67: =B67-C67+D67-G67 -> 18 | I67: =G67*6 -> 12
A68: Maracujá | B68: =H40 -> 27 | E68: 5 | F68: 3 | G68: =E68-F68 -> 2 | H68: =B68-C68+D68-G68 -> 25 | I68: =G68*6 -> 12
A69: Maracujá com nutella | B69: =H41 -> 8 | E69: 5 | F69: 3 | G69: =E69-F69 -> 2 | H69: =B69-C69+D69-G69 -> 6 | I69: =G69*6 -> 12
A70: Milho verde | B70: =H42 -> 2 | E70: 2 | F70: 1 | G70: =E70-F70 -> 1 | H70: =B70-C70+D70-G70 -> 1 | I70: =G70*6 -> 6
A71: Morango | B71: =H43 -> 28 | E71: 4 | F71: 4 | G71: =E71-F71 -> 0 | H71: =B71-C71+D71-G71 -> 28 | I71: =G71*6 -> 0
A72: Morango com Nutella | B72: =H44 -> 20 | E72: 6 | F72: 3 | G72: =E72-F72 -> 3 | H72: =B72-C72+D72-G72 -> 17 | I72: =G72*6 -> 18
A73: Mousse de limão | B73: =H45 -> 14 | E73: 3 | F73: 3 | G73: =E73-F73 -> 0 | H73: =B73-C73+D73-G73 -> 14 | I73: =G73*6 -> 0
A74: Ninho com Nutella | B74: =H46 -> 41 | E74: 10 | F74: 6 | G74: =E74-F74 -> 4 | H74: =B74-C74+D74-G74 -> 37 | I74: =G74*6 -> 24
A75: Ninho com Morango | B75: =H47 -> 13 | E75: 4 | F75: 3 | G75: =E75-F75 -> 1 | H75: =B75-C75+D75-G75 -> 12 | I75: =G75*6 -> 6
A76: Oreo | B76: =H48 -> 11 | E76: 4 | F76: 2 | G76: =E76-F76 -> 2 | H76: =B76-C76+D76-G76 -> 9 | I76: =G76*6 -> 12
... A81: Zero lactose morango | B81: =H53 -> 18 | E81: 2 | F81: 1 | G81: =E81-F81 -> 1 | H81: =B81-C81+D81-G81 -> 17 | I81: =G81*6 -> 6
A82: TOTAL | B82: =SUM(B59:B81) -> 460 | E82: =SUM(E58:E81) -> 126 | F82: =SUM(F58:F81) -> 74 | G82: =SUM(G58:G81) -> 52 | H82: =SUM(H59:H81) -> 443 | I82: =SUM(I58:I81) -> 312
F83: Saldo
B85: Data: 08/04/2026
A86: SABORES | B86: Estoque Inicial | C86: Furou | D86: Fez | E86: Quantidade de Geladinhos | F86: Voltaram | G86: Vendidos | H86: Estoque Final | I86: R$
A87: Abacate | B87: =H59 -> 23 | E87: 6 | F87: 2 | G87: =E87-F87 -> 4 | H87: =B87-C87+D87-G87 -> 19 | I87: =G87*6 -> 24
A88: Abacaxi | B88: =H60 -> 20 | E88: 3 | F88: 3 | G88: =E88-F88 -> 0 | H88: =B88-C88+D88-G88 -> 20 | I88: =G88*6 -> 0
A89: Açaí | B89: =H61 -> 21 | E89: 4 | F89: 4 | G89: =E89-F89 -> 0 | H89: =B89-C89+D89-G89 -> 21 | I89: =G89*6 -> 0
A90: Amendoim | B90: =H62 -> 22 | E90: 6 | F90: 4 | G90: =E90-F90 -> 2 | H90: =B90-C90+D90-G90 -> 20 | I90: =G90*6 -> 12
A91: Brigadeiro | B91: =H63 -> 14 | E91: 4 | F91: 4 | G91: =E91-F91 -> 0 | H91: =B91-C91+D91-G91 -> 14 | I91: =G91*6 -> 0
A92: Buriti | B92: =H64 -> 40 | E92: 6 | F92: 5 | G92: =E92-F92 -> 1 | H92: =B92-C92+D92-G92 -> 39 | I92: =G92*6 -> 6
A93: Coco | B93: =H65 -> 12 | E93: 5 | F93: 5 | G93: =E93-F93 -> 0 | H93: =B93-C93+D93-G93 -> 12 | I93: =G93*6 -> 0
A94: Coco Queimado | B94: =H66 -> 8 | E94: 3 | F94: 3 | G94: =E94-F94 -> 0 | H94: =B94-C94+D94-G94 -> 8 | I94: =G94*6 -> 0
A95: Cupuaçu | B95: =H67 -> 18 | E95: 6 | F95: 6 | G95: =E95-F95 -> 0 | H95: =B95-C95+D95-G95 -> 18 | I95: =G95*6 -> 0
A96: Maracujá | B96: =H68 -> 25 | E96: 5 | F96: 4 | G96: =E96-F96 -> 1 | H96: =B96-C96+D96-G96 -> 24 | I96: =G96*6 -> 6
A97: Maracujá com nutella | B97: =H69 -> 6 | D97: 30 | E97: 5 | F97: 1 | G97: =E97-F97 -> 4 | H97: =B97-C97+D97-G97 -> 32 | I97: =G97*6 -> 24
A98: Milho verde | B98: =H70 -> 1 | E98: 1 | F98: 0 | G98: =E98-F98 -> 1 | H98: =B98-C98+D98-G98 -> 0 | I98: =G98*6 -> 6
A99: Morango | B99: =H71 -> 28 | E99: 4 | F99: 4 | G99: =E99-F99 -> 0 | H99: =B99-C99+D99-G99 -> 28 | I99: =G99*6 -> 0
A100: Morango com Nutella | B100: =H72 -> 17 | E100: 6 | F100: 4 | G100: =E100-F100 -> 2 | H100: =B100-C100+D100-G100 -> 15 | I100: =G100*6 -> 12
A101: Mousse de limão | B101: =H73 -> 14 | E101: 3 | F101: 3 | G101: =E101-F101 -> 0 | H101: =B101-C101+D101-G101 -> 14 | I101: =G101*6 -> 0
A102: Ninho com Nutella | B102: =H74 -> 37 | E102: 8 | F102: 2 | G102: =E102-F102 -> 6 | H102: =B102-C102+D102-G102 -> 31 | I102: =G102*6 -> 36
A103: Ninho com Morango | B103: =H75 -> 12 | E103: 4 | F103: 4 | G103: =E103-F103 -> 0 | H103: =B103-C103+D103-G103 -> 12 | I103: =G103*6 -> 0
A104: Oreo | B104: =H76 -> 9 | E104: 4 | F104: 3 | G104: =E104-F104 -> 1 | H104: =B104-C104+D104-G104 -> 8 | I104: =G104*6 -> 6
A105: Prestígio | B105: =H77 -> 34 | E105: 8 | F105: 5 | G105: =E105-F105 -> 3 | H105: =B105-C105+D105-G105 -> 31 | I105: =G105*6 -> 18
A106: Pudim | B106: =H78 -> 38 | D106: 32 | E106: 28 | F106: 13 | G106: =E106-F106 -> 15 | H106: =B106-C106+D106-G106 -> 55 | I106: =G106*6 -> 90
A107: Uva | B107: =H79 -> 12 | E107: 2 | F107: 2 | G107: =E107-F107 -> 0 | H107: =B107-C107+D107-G107 -> 12 | I107: =G107*6 -> 0
A108: Zero lactose coco | B108: =H80 -> 15 | E108: 2 | F108: 2 | G108: =E108-F108 -> 0 | H108: =B108-C108+D108-G108 -> 15 | I108: =G108*6 -> 0
A109: Zero lactose morango | B109: =H81 -> 17 | E109: 2 | F109: 2 | G109: =E109-F109 -> 0 | H109: =B109-C109+D109-G109 -> 17 | I109: =G109*6 -> 0
...

Sheet MARÇO26
B1: Data: 02/03/2026
A2: SABORES | B2: Estoque Inicial | C2: Furou | D2: Fez | E2: Quantidade de Geladinhos | F2: Voltaram | G2: Vendidos | H2: Estoque Final | I2: R$
A3: Abacate | B3: =FEVEREIRO26!H448 -> 19 | E3: 6 | F3: 6 | G3: =E3-F3 -> 0 | H3: =B3-C3+D3-G3 -> 19 | I3: =G3*6 -> 0
A4: Abacaxi | B4: =FEVEREIRO26!H449 -> 41 | E4: 6 | F4: 6 | G4: =E4-F4 -> 0 | H4: =B4-C4+D4-G4 -> 41 | I4: =G4*6 -> 0
A5: Açaí | B5: =FEVEREIRO26!H450 -> 40 | E5: 6 | F5: 6 | G5: =E5-F5 -> 0 | H5: =B5-C5+D5-G5 -> 40 | I5: =G5*6 -> 0
A6: Amendoim | B6: =FEVEREIRO26!H451 -> 31 | C6: 1 | E6: 6 | F6: 5 | G6: =E6-F6 -> 1 | H6: =B6-C6+D6-G6 -> 29 | I6: =G6*6 -> 6
A7: Brigadeiro | B7: =FEVEREIRO26!H452 -> 27 | E7: 4 | F7: 3 | G7: =E7-F7 -> 1 | H7: =B7-C7+D7-G7 -> 26 | I7: =G7*6 -> 6
A8: Buriti | B8: =FEVEREIRO26!H453 -> 14 | E8: 6 | F8: 5 | G8: =E8-F8 -> 1 | H8: =B8-C8+D8-G8 -> 13 | I8: =G8*6 -> 6
A9: Coco | B9: =FEVEREIRO26!H454 -> 25 | E9: 4 | F9: 4 | G9: =E9-F9 -> 0 | H9: =B9-C9+D9-G9 -> 25 | I9: =G9*6 -> 0
A10: Coco Queimado | B10: =FEVEREIRO26!H455 -> 29 | E10: 4 | F10: 4 | G10: =E10-F10 -> 0 | H10: =B10-C10+D10-G10 -> 29 | I10: =G10*6 -> 0
A11: Cupuaçu | B11: =FEVEREIRO26!H456 -> 27 | E11: 4 | F11: 4 | G11: =E11-F11 -> 0 | H11: =B11-C11+D11-G11 -> 27 | I11: =G11*6 -> 0
A12: Maracujá | B12: =FEVEREIRO26!H457 -> 9 | E12: 4 | F12: 3 | G12: =E12-F12 -> 1 | H12: =B12-C12+D12-G12 -> 8 | I12: =G12*6 -> 6
A13: Maracujá com nutella | B13: =FEVEREIRO26!H458 -> 15 | E13: 4 | F13: 4 | G13: =E13-F13 -> 0 | H13: =B13-C13+D13-G13 -> 15 | I13: =G13*6 -> 0
A14: Milho verde | B14: =FEVEREIRO26!H459 -> 10 | E14: 2 | F14: 1 | G14: =E14-F14 -> 1 | H14: =B14-C14+D14-G14 -> 9 | I14: =G14*6 -> 6
A15: Morango | B15: =FEVEREIRO26!H460 -> 8 | E15: 4 | F15: 3 | G15: =E15-F15 -> 1 | H15: =B15-C15+D15-G15 -> 7 | I15: =G15*6 -> 6
A16: Morango com Nutella | B16: =FEVEREIRO26!H461 -> 35 | E16: 6 | F16: 4 | G16: =E16-F16 -> 2 | H16: =B16-C16+D16-G16 -> 33 | I16: =G16*6 -> 12
A17: Mousse de limão | B17: =FEVEREIRO26!H462 -> 24 | E17: 4 | F17: 4 | G17: =E17-F17 -> 0 | H17: =B17-C17+D17-G17 -> 24 | I17: =G17*6 -> 0
A18: Ninho com Nutella | B18: =FEVEREIRO26!H463 -> 27 | E18: 8 | F18: 3 | G18: =E18-F18 -> 5 | H18: =B18-C18+D18-G18 -> 22 | I18: =G18*6 -> 30
... A24: Zero lactose morango | B24: =FEVEREIRO26!H469 -> 7 | E24: 2 | F24: 2 | G24: =E24-F24 -> 0 | H24: =B24-C24+D24-G24 -> 7 | I24: =G24*6 -> 0
A25: TOTAL | B25: =SUM(B3:B24) -> 505 | E25: =SUM(E2:E24) -> 100 | F25: =SUM(F2:F24) -> 84 | G25: =SUM(G2:G24) -> 16 | H25: =SUM(H3:H24) -> 488 | I25: =SUM(I2:I24) -> 96
F26: Saldo
B28: Data: 03/03/2026
A29: SABORES | B29: Estoque Inicial | C29: Furou | D29: Fez | E29: Quantidade de Geladinhos | F29: Voltaram | G29: Vendidos | H29: Estoque Final | I29: R$
A30: Abacate | B30: =H3 -> 19 | E30: 6 | F30: 4 | G30: =E30-F30 -> 2 | H30: =B30-C30+D30-G30 -> 17 | I30: =G30*6 -> 12
A31: Abacaxi | B31: =H4 -> 41 | E31: 4 | F31: 4 | G31: =E31-F31 -> 0 | H31: =B31-C31+D31-G31 -> 41 | I31: =G31*6 -> 0
A32: Açaí | B32: =H5 -> 40 | E32: 4 | F32: 2 | G32: =E32-F32 -> 2 | H32: =B32-C32+D32-G32 -> 38 | I32: =G32*6 -> 12
A33: Amendoim | B33: =H6 -> 29 | E33: 6 | F33: 6 | G33: =E33-F33 -> 0 | H33: =B33-C33+D33-G33 -> 29 | I33: =G33*6 -> 0
A34: Brigadeiro | B34: =H7 -> 26 | E34: 4 | F34: 2 | G34: =E34-F34 -> 2 | H34: =B34-C34+D34-G34 -> 24 | I34: =G34*6 -> 12
A35: Buriti | B35: =H8 -> 13 | E35: 4 | F35: 3 | G35: =E35-F35 -> 1 | H35: =B35-C35+D35-G35 -> 12 | I35: =G35*6 -> 6
A36: Coco | B36: =H9 -> 25 | E36: 4 | F36: 3 | G36: =E36-F36 -> 1 | H36: =B36-C36+D36-G36 -> 24 | I36: =G36*6 -> 6
A37: Coco Queimado | B37: =H10 -> 29 | E37: 4 | F37: 3 | G37: =E37-F37 -> 1 | H37: =B37-C37+D37-G37 -> 28 | I37: =G37*6 -> 6
A38: Cupuaçu | B38: =H11 -> 27 | E38: 4 | F38: 2 | G38: =E38-F38 -> 2 | H38: =B38-C38+D38-G38 -> 25 | I38: =G38*6 -> 12
A39: Maracujá | B39: =H12 -> 8 | E39: 4 | F39: 4 | G39: =E39-F39 -> 0 | H39: =B39-C39+D39-G39 -> 8 | I39: =G39*6 -> 0
A40: Maracujá com nutella | B40: =H13 -> 15 | E40: 4 | F40: 0 | G40: =E40-F40 -> 4 | H40: =B40-C40+D40-G40 -> 11 | I40: =G40*6 -> 24
A41: Milho verde | B41: =H14 -> 9 | E41: 2 | F41: 2 | G41: =E41-F41 -> 0 | H41: =B41-C41+D41-G41 -> 9 | I41: =G41*6 -> 0
A42: Morango | B42: =H15 -> 7 | D42: 30 | E42: 4 | F42: 3 | G42: =E42-F42 -> 1 | H42: =B42-C42+D42-G42 -> 36 | I42: =G42*6 -> 6
A43: Morango com Nutella | B43: =H16 -> 33 | E43: 6 | F43: 3 | G43: =E43-F43 -> 3 | H43: =B43-C43+D43-G43 -> 30 | I43: =G43*6 -> 18
A44: Mousse de limão | B44: =H17 -> 24 | E44: 4 | F44: 4 | G44: =E44-F44 -> 0 | H44: =B44-C44+D44-G44 -> 24 | I44: =G44*6 -> 0
A45: Ninho com Nutella | B45: =H18 -> 22 | E45: 8 | F45: 3 | G45: =E45-F45 -> 5 | H45: =B45-C45+D45-G45 -> 17 | I45: =G45*6 -> 30
A46: Ninho com Morango | B46: =H19 -> 17 | E46: 4 | F46: 1 | G46: =E46-F46 -> 3 | H46: =B46-C46+D46-G46 -> 14 | I46: =G46*6 -> 18
A47: Oreo | B47: =H20 -> 30 | E47: 3 | F47: 3 | G47: =E47-F47 -> 0 | H47: =B47-C47+D47-G47 -> 30 | I47: =G47*6 -> 0
A48: Prestígio | B48: =H21 -> 21 | E48: 8 | F48: 5 | G48: =E48-F48 -> 3 | H48: =B48-C48+D48-G48 -> 18 | I48: =G48*6 -> 18
A49: Uva | B49: =H22 -> 25 | E49: 2 | F49: 2 | G49: =E49-F49 -> 0 | H49: =B49-C49+D49-G49 -> 25 | I49: =G49*6 -> 0
A50: Zero lactose coco | B50: =H23 -> 21 | E50: 2 | F50: 1 | G50: =E50-F50 -> 1 | H50: =B50-C50+D50-G50 -> 20 | I50: =G50*6 -> 6
A51: Zero lactose morango | B51: =H24 -> 7 | E51: 2 | F51: 1 | G51: =E51-F51 -> 1 | H51: =B51-C51+D51-G51 -> 6 | I51: =G51*6 -> 6
A52: TOTAL | B52: =SUM(B30:B51) -> 488 | E52: =SUM(E29:E51) -> 93 | F52: =SUM(F29:F51) -> 61 | G52: =SUM(G29:G51) -> 32 | H52: =SUM(H30:H51) -> 486 | I52: =SUM(I29:I51) -> 192
F53: Saldo
B55: Data: 04/03/2026
A56: SABORES | B56: Estoque Inicial | C56: Furou | D56: Fez | E56: Quantidade de Geladinhos | F56: Voltaram | G56: Vendidos | H56: Estoque Final | I56: R$
A57: Abacate | B57: =H30 -> 17 | E57: 6 | F57: 3 | G57: =E57-F57 -> 3 | H57: =B57-C57+D57-G57 -> 14 | I57: =G57*6 -> 18
A58: Abacaxi | B58: =H31 -> 41 | C58: 1 | E58: 4 | F58: 3 | G58: =E58-F58 -> 1 | H58: =B58-C58+D58-G58 -> 39 | I58: =G58*6 -> 6
A59: Açaí | B59: =H32 -> 38 | C59: 1 | E59: 4 | F59: 3 | G59: =E59-F59 -> 1 | H59: =B59-C59+D59-G59 -> 36 | I59: =G59*6 -> 6
A60: Amendoim | B60: =H33 -> 29 | E60: 6 | F60: 4 | G60: =E60-F60 -> 2 | H60: =B60-C60+D60-G60 -> 27 | I60: =G60*6 -> 12
A61: Brigadeiro | B61: =H34 -> 24 | E61: 4 | F61: 2 | G61: =E61-F61 -> 2 | H61: =B61-C61+D61-G61 -> 22 | I61: =G61*6 -> 12
A62: Buriti | B62: =H35 -> 12 | E62: 4 | F62: 2 | G62: =E62-F62 -> 2 | H62: =B62-C62+D62-G62 -> 10 | I62: =G62*6 -> 12
A63: Coco | B63: =H36 -> 24 | E63: 4 | F63: 2 | G63: =E63-F63 -> 2 | H63: =B63-C63+D63-G63 -> 22 | I63: =G63*6 -> 12
A64: Coco Queimado | B64: =H37 -> 28 | E64: 4 | F64: 2 | G64: =E64-F64 -> 2 | H64: =B64-C64+D64-G64 -> 26 | I64: =G64*6 -> 12
A65: Cupuaçu | B65: =H38 -> 25 | E65: 4 | F65: 2 | G65: =E65-F65 -> 2 | H65: =B65-C65+D65-G65 -> 23 | I65: =G65*6 -> 12
A66: Maracujá | B66: =H39 -> 8 | D66: 33 | E66: 4 | F66: 0 | G66: =E66-F66 -> 4 | H66: =B66-C66+D66-G66 -> 37 | I66: =G66*6 -> 24
A67: Maracujá com nutella | B67: =H40 -> 11 | C67: 2 | D67: 29 | E67: 5 | F67: 3 | G67: =E67-F67 -> 2 | H67: =B67-C67+D67-G67 -> 36 | I67: =G67*6 -> 12
A68: Milho verde | B68: =H41 -> 9 | E68: 2 | F68: 2 | G68: =E68-F68 -> 0 | H68: =B68-C68+D68-G68 -> 9 | I68: =G68*6 -> 0
A69: Morango | B69: =H42 -> 36 | E69: 4 | F69: 4 | G69: =E69-F69 -> 0 | H69: =B69-C69+D69-G69 -> 36 | I69: =G69*6 -> 0
A70: Morango com Nutella | B70: =H43 -> 30 | E70: 6 | F70: 3 | G70: =E70-F70 -> 3 | H70: =B70-C70+D70-G70 -> 27 | I70: =G70*6 -> 18
A71: Mousse de limão | B71: =H44 -> 24 | C71: 1 | E71: 3 | F71: 3 | G71: =E71-F71 -> 0 | H71: =B71-C71+D71-G71 -> 23 | I71: =G71*6 -> 0
A72: Ninho com Nutella | B72: =H45 -> 17 | E72: 8 | F72: 3 | G72: =E72-F72 -> 5 | H72: =B72-C72+D72-G72 -> 12 | I72: =G72*6 -> 30
A73: Ninho com Morango | B73: =H46 -> 14 | E73: 4 | F73: 3 | G73: =E73-F73 -> 1 | H73: =B73-C73+D73-G73 -> 13 | I73: =G73*6 -> 6
A74: Oreo | B74: =H47 -> 30 | E74: 3 | F74: 3 | G74: =E74-F74 -> 0 | H74: =B74-C74+D74-G74 -> 30 | I74: =G74*6 -> 0
A75: Prestígio | B75: =H48 -> 18 | E75: 6 | F75: 5 | G75: =E75-F75 -> 1 | H75: =B75-C75+D75-G75 -> 17 | I75: =G75*6 -> 6
A76: Uva | B76: =H49 -> 25 | E76: 2 | F76: 2 | G76: =E76-F76 -> 0 | H76: =B76-C76+D76-G76 -> 25 | I76: =G76*6 -> 0
A77: Zero lactose coco | B77: =H50 -> 20 | E77: 2 | F77: 2 | G77: =E77-F77 -> 0 | H77: =B77-C77+D77-G77 -> 20 | I77: =G77*6 -> 0
A78: Zero lactose morango | B78: =H51 -> 6 | E78: 2 | F78: 1 | G78: =E78-F78 -> 1 | H78: =B78-C78+D78-G78 -> 5 | I78: =G78*6 -> 6
A79: TOTAL | B79: =SUM(B57:B78) -> 486 | E79: =SUM(E56:E78) -> 91 | F79: =SUM(F56:F78) -> 57 | G79: =SUM(G56:G78) -> 34 | H79: =SUM(H57:H78) -> 509 | I79: =SUM(I56:I78) -> 204
F80: Saldo
B82: Data: 05/03/2026
A83: SABORES | B83: Estoque Inicial | C83: Furou | D83: Fez | E83: Quantidade de Geladinhos | F83: Voltaram | G83: Vendidos | H83: Estoque Final | I83: R$
A84: Abacate | B84: =H57 -> 14 | C84: 2 | E84: 9 | F84: 5 | G84: =E84-F84 -> 4 | H84: =B84-C84+D84-G84 -> 8 | I84: =G84*6 -> 24
A85: Abacaxi | B85: =H58 -> 39 | E85: 4 | F85: 3 | G85: =E85-F85 -> 1 | H85: =B85-C85+D85-G85 -> 38 | I85: =G85*6 -> 6
A86: Açaí | B86: =H59 -> 36 | E86: 4 | F86: 2 | G86: =E86-F86 -> 2 | H86: =B86-C86+D86-G86 -> 34 | I86: =G86*6 -> 12
A87: Amendoim | B87: =H60 -> 27 | E87: 6 | F87: 6 | G87: =E87-F87 -> 0 | H87: =B87-C87+D87-G87 -> 27 | I87: =G87*6 -> 0
A88: Brigadeiro | B88: =H61 -> 22 | E88: 4 | F88: 3 | G88: =E88-F88 -> 1 | H88: =B88-C88+D88-G88 -> 21 | I88: =G88*6 -> 6
A89: Buriti | B89: =H62 -> 10 | C89: 2 | E89: 4 | F89: 3 | G89: =E89-F89 -> 1 | H89: =B89-C89+D89-G89 -> 7 | I89: =G89*6 -> 6
A90: Coco | B90: =H63 -> 22 | E90: 4 | F90: 4 | G90: =E90-F90 -> 0 | H90: =B90-C90+D90-G90 -> 22 | I90: =G90*6 -> 0
A91: Coco Queimado | B91: =H64 -> 26 | E91: 4 | F91: 4 | G91: =E91-F91 -> 0 | H91: =B91-C91+D91-G91 -> 26 | I91: =G91*6 -> 0
A92: Cupuaçu | B92: =H65 -> 23 | E92: 4 | F92: 3 | G92: =E92-F92 -> 1 | H92: =B92-C92+D92-G92 -> 22 | I92: =G92*6 -> 6
A93: Maracujá | B93: =H66 -> 37 | E93: 4 | F93: 3 | G93: =E93-F93 -> 1 | H93: =B93-C93+D93-G93 -> 36 | I93: =G93*6 -> 6
A94: Maracujá com nutella | B94: =H67 -> 36 | E94: 5 | F94: 3 | G94: =E94-F94 -> 2 | H94: =B94-C94+D94-G94 -> 34 | I94: =G94*6 -> 12
A95: Milho verde | B95: =H68 -> 9 | E95: 2 | F95: 2 | G95: =E95-F95 -> 0 | H95: =B95-C95+D95-G95 -> 9 | I95: =G95*6 -> 0
A96: Morango | B96: =H69 -> 36 | E96: 4 | F96: 3 | G96: =E96-F96 -> 1 | H96: =B96-C96+D96-G96 -> 35 | I96: =G96*6 -> 6
A97: Morango com Nutella | B97: =H70 -> 27 | E97: 6 | F97: 2 | G97: =E97-F97 -> 4 | H97: =B97-C97+D97-G97 -> 23 | I97: =G97*6 -> 24
A98: Mousse de limão | B98: =H71 -> 23 | E98: 3 | F98: 3 | G98: =E98-F98 -> 0 | H98: =B98-C98+D98-G98 -> 23 | I98: =G98*6 -> 0
A99: Ninho com Nutella | B99: =H72 -> 12 | C99: 1 | D99: 30 | E99: 8 | F99: 0 | G99: =E99-F99 -> 8 | H99: =B99-C99+D99-G99 -> 33 | I99: =G99*6 -> 48
A100: Ninho com Morango | B100: =H73 -> 13 | C100: 4 | E100: 4 | F100: 4 | G100: =E100-F100 -> 0 | H100: =B100-C100+D100-G100 -> 9 | I100: =G100*6 -> 0
A101: Oreo | B101: =H74 -> 30 | E101: 3 | F101: 3 | G101: =E101-F101 -> 0 | H101: =B101-C101+D101-G101 -> 30 | I101: =G101*6 -> 0
A102: Prestígio | B102: =H75 -> 17 | E102: 6 | F102: 0 | G102: =E102-F102 -> 6 | H102: =B102-C102+D102-G102 -> 11 | I102: =G102*6 -> 36
A103: Uva | B103: =H76 -> 25 | E103: 2 | F103: 1 | G103: =E103-F103 -> 1 | H103: =B103-C103+D103-G103 -> 24 | I103: =G103*6 -> 6
A104: Zero lactose coco | B104: =H77 -> 20 | E104: 2 | F104: 1 | G104: =E104-F104 -> 1 | H104: =B104-C104+D104-G104 -> 19 | I104: =G104*6 -> 6
A105: Zero lactose morango | B105: =H78 -> 5 | E105: 2 | F105: 2 | G105: =E105-F105 -> 0 | H105: =B105-C105+D105-G105 -> 5 | I105: =G105*6 -> 0
A106: TOTAL | B106: =SUM(B84:B105) -> 509 | E106: =SUM(E83:E105) -> 94 | F106: =SUM(F83:F105) -> 60 | G106: =SUM(G83:G105) -> 34 | H106: =SUM(H84:H105) -> 496 | I106: =SUM(I83:I105) -> 204
F107: Saldo
B109: Data: 06/03/2026
...

Sheet FEVEREIRO26
B1: Data: 02/02/2026
A2: SABORES | B2: Estoque Inicial | C2: Furou | D2: Fez | E2: Quantidade de Geladinhos | F2: Voltaram | G2: Vendidos | H2: Estoque Final | I2: R$
A3: Abacate | B3: 35 | E3: 6 | F3: 5 | G3: =E3-F3 -> 1 | H3: =B3-C3+D3-G3 -> 34 | I3: =G3*6 -> 6
A4: Abacaxi | B4: 12 | E4: 6 | F4: 4 | G4: =E4-F4 -> 2 | H4: =B4-C4+D4-G4 -> 10 | I4: =G4*6 -> 12
A5: Açaí | B5: 37 | E5: 6 | F5: 6 | G5: =E5-F5 -> 0 | H5: =B5-C5+D5-G5 -> 37 | I5: =G5*6 -> 0
A6: Amendoim | B6: 23 | C6: 6 | E6: 7 | F6: 5 | G6: =E6-F6 -> 2 | H6: =B6-C6+D6-G6 -> 15 | I6: =G6*6 -> 12
A7: Brigadeiro | B7: 25 | E7: 4 | F7: 3 | G7: =E7-F7 -> 1 | H7: =B7-C7+D7-G7 -> 24 | I7: =G7*6 -> 6
A8: Buriti | B8: 40 | E8: 8 | F8: 5 | G8: =E8-F8 -> 3 | H8: =B8-C8+D8-G8 -> 37 | I8: =G8*6 -> 18 | L8: =SUM(I24+I51+I78+I106+I134+I162+I190+I218+I246+I274+I302+I330+I358+I386+I414+I442+I470) -> 3774
A9: Coco | B9: 33 | E9: 5 | F9: 4 | G9: =E9-F9 -> 1 | H9: =B9-C9+D9-G9 -> 32 | I9: =G9*6 -> 6
A10: Coco Queimado | B10: 22 | E10: 4 | F10: 2 | G10: =E10-F10 -> 2 | H10: =B10-C10+D10-G10 -> 20 | I10: =G10*6 -> 12
A11: Cupuaçu | B11: 13 | E11: 6 | F11: 6 | G11: =E11-F11 -> 0 | H11: =B11-C11+D11-G11 -> 13 | I11: =G11*6 -> 0
A12: Maracujá | B12: 32 | E12: 6 | F12: 6 | G12: =E12-F12 -> 0 | H12: =B12-C12+D12-G12 -> 32 | I12: =G12*6 -> 0
A13: Maracujá com nutella | B13: 20 | E13: 6 | F13: 6 | G13: =E13-F13 -> 0 | H13: =B13-C13+D13-G13 -> 20 | I13: =G13*6 -> 0
A14: Milho verde | B14: 14 | E14: 2 | F14: 2 | G14: =E14-F14 -> 0 | H14: =B14-C14+D14-G14 -> 14 | I14: =G14*6 -> 0
A15: Morango | B15: 29 | E15: 5 | F15: 4 | G15: =E15-F15 -> 1 | H15: =B15-C15+D15-G15 -> 28 | I15: =G15*6 -> 6
A16: Morango com Nutella | B16: 17 | E16: 6 | F16: 5 | G16: =E16-F16 -> 1 | H16: =B16-C16+D16-G16 -> 16 | I16: =G16*6 -> 6
A17: Mousse de limão | B17: 10 | E17: 4 | F17: 3 | G17: =E17-F17 -> 1 | H17: =B17-C17+D17-G17 -> 9 | I17: =G17*6 -> 6
A18: Ninho com Nutella | B18: 35 | E18: 10 | F18: 3 | G18: =E18-F18 -> 7 | H18: =B18-C18+D18-G18 -> 28 | I18: =G18*6 -> 42
A19: Ninho com Morango | B19: 19 | E19: 6 | F19: 3 | G19: =E19-F19 -> 3 | H19: =B19-C19+D19-G19 -> 16 | I19: =G19*6 -> 18
A20: Oreo | B20: 17 | E20: 4 | F20: 3 | G20: =E20-F20 -> 1 | H20: =B20-C20+D20-G20 -> 16 | I20: =G20*6 -> 6
... A23: Zero lactose | B23: 24 | E23: 4 | F23: 3 | G23: =E23-F23 -> 1 | H23: =B23-C23+D23-G23 -> 23 | I23: =G23*6 -> 6
A24: TOTAL | B24: =SUM(B3:B23) -> 512 | E24: =SUM(E2:E23) -> 115 | F24: =SUM(F2:F23) -> 87 | G24: =SUM(G2:G23) -> 28 | H24: =SUM(H3:H23) -> 478 | I24: =SUM(I2:I23) -> 168
F25: Saldo
E26: Valor Total de Venda do dia - GELADINHOS | I26: =SUM(I3:I23) -> 168
B28: Data: 03/02/2026
A29: SABORES | B29: Estoque Inicial | C29: Furou | D29: Fez | E29: Quantidade de Geladinhos | F29: Voltaram | G29: Vendidos | H29: Estoque Final | I29: R$
A30: Abacate | B30: =H3 -> 34 | E30: 6 | F30: 0 | G30: =E30-F30 -> 6 | H30: =B30-C30+D30-G30 -> 28 | I30: =G30*6 -> 36
A31: Abacaxi | B31: =H4 -> 10 | E31: 6 | F31: 5 | G31: =E31-F31 -> 1 | H31: =B31-C31+D31-G31 -> 9 | I31: =G31*6 -> 6
A32: Açaí | B32: =H5 -> 37 | E32: 6 | F32: 6 | G32: =E32-F32 -> 0 | H32: =B32-C32+D32-G32 -> 37 | I32: =G32*6 -> 0
A33: Amendoim | B33: =H6 -> 15 | E33: 6 | F33: 3 | G33: =E33-F33 -> 3 | H33: =B33-C33+D33-G33 -> 12 | I33: =G33*6 -> 18
A34: Brigadeiro | B34: =H7 -> 24 | E34: 4 | F34: 3 | G34: =E34-F34 -> 1 | H34: =B34-C34+D34-G34 -> 23 | I34: =G34*6 -> 6
A35: Buriti | B35: =H8 -> 37 | E35: 6 | F35: 4 | G35: =E35-F35 -> 2 | H35: =B35-C35+D35-G35 -> 35 | I35: =G35*6 -> 12
A36: Coco | B36: =H9 -> 32 | E36: 5 | F36: 3 | G36: =E36-F36 -> 2 | H36: =B36-C36+D36-G36 -> 30 | I36: =G36*6 -> 12
A37: Coco Queimado | B37: =H10 -> 20 | E37: 4 | F37: 1 | G37: =E37-F37 -> 3 | H37: =B37-C37+D37-G37 -> 17 | I37: =G37*6 -> 18
A38: Cupuaçu | B38: =H11 -> 13 | E38: 6 | F38: 4 | G38: =E38-F38 -> 2 | H38: =B38-C38+D38-G38 -> 11 | I38: =G38*6 -> 12 | L38: 31
A39: Maracujá | B39: =H12 -> 32 | E39: 6 | F39: 4 | G39: =E39-F39 -> 2 | H39: =B39-C39+D39-G39 -> 30 | I39: =G39*6 -> 12 | L39: 3131
A40: Maracujá com nutella | B40: =H13 -> 20 | E40: 6 | F40: 6 | G40: =E40-F40 -> 0 | H40: =B40-C40+D40-G40 -> 20 | I40: =G40*6 -> 0
A41: Milho verde | B41: =H14 -> 14 | E41: 2 | F41: 2 | G41: =E41-F41 -> 0 | H41: =B41-C41+D41-G41 -> 14 | I41: =G41*6 -> 0
A42: Morango | B42: =H15 -> 28 | E42: 5 | F42: 5 | G42: =E42-F42 -> 0 | H42: =B42-C42+D42-G42 -> 28 | I42: =G42*6 -> 0
A43: Morango com Nutella | B43: =H16 -> 16 | E43: 6 | F43: 2 | G43: =E43-F43 -> 4 | H43: =B43-C43+D43-G43 -> 12 | I43: =G43*6 -> 24
A44: Mousse de limão | B44: =H17 -> 9 | E44: 4 | F44: 2 | G44: =E44-F44 -> 2 | H44: =B44-C44+D44-G44 -> 7 | I44: =G44*6 -> 12
A45: Ninho com Nutella | B45: =H18 -> 28 | E45: 10 | F45: 5 | G45: =E45-F45 -> 5 | H45: =B45-C45+D45-G45 -> 23 | I45: =G45*6 -> 30
A46: Ninho com Morango | B46: =H19 -> 16 | E46: 6 | F46: 6 | G46: =E46-F46 -> 0 | H46: =B46-C46+D46-G46 -> 16 | I46: =G46*6 -> 0
A47: Oreo | B47: =H20 -> 16 | E47: 4 | F47: 3 | G47: =E47-F47 -> 1 | H47: =B47-C47+D47-G47 -> 15 | I47: =G47*6 -> 6
A48: Prestígio | B48: =H21 -> 38 | C48: 1 | E48: 8 | F48: 8 | G48: =E48-F48 -> 0 | H48: =B48-C48+D48-G48 -> 37 | I48: =G48*6 -> 0
A49: Uva | B49: =H22 -> 16 | E49: 2 | F49: 2 | G49: =E49-F49 -> 0 | H49: =B49-C49+D49-G49 -> 16 | I49: =G49*6 -> 0
A50: Zero lactose | B50: =H23 -> 23 | E50: 4 | F50: 2 | G50: =E50-F50 -> 2 | H50: =B50-C50+D50-G50 -> 21 | I50: =G50*6 -> 12
A51: TOTAL | B51: =SUM(B30:B50) -> 478 | E51: =SUM(E29:E50) -> 112 | F51: =SUM(F29:F50) -> 76 | G51: =SUM(G29:G50) -> 36 | H51: =SUM(H30:H50) -> 441 | I51: =SUM(I29:I50) -> 216
F52: Saldo
E53: Valor Total de Venda do dia - GELADINHOS | I53: =SUM(I30:I50) -> 216
B55: Data: 04/02/2026
A56: SABORES | B56: Estoque Inicial | C56: Furou | D56: Fez | E56: Quantidade de Geladinhos | F56: Voltaram | G56: Vendidos | H56: Estoque Final | I56: R$
A57: Abacate | B57: =H30 -> 28 | E57: 6 | F57: 1 | G57: =E57-F57 -> 5 | H57: =B57-C57+D57-G57 -> 23 | I57: =G57*6 -> 30
A58: Abacaxi | B58: =H31 -> 9 | D58: 32 | E58: 6 | F58: 2 | G58: =E58-F58 -> 4 | H58: =B58-C58+D58-G58 -> 37 | I58: =G58*6 -> 24
A59: Açaí | B59: =H32 -> 37 | E59: 6 | F59: 4 | G59: =E59-F59 -> 2 | H59: =B59-C59+D59-G59 -> 35 | I59: =G59*6 -> 12
A60: Amendoim | B60: =H33 -> 12 | E60: 6 | F60: 3 | G60: =E60-F60 -> 3 | H60: =B60-C60+D60-G60 -> 9 | I60: =G60*6 -> 18
A61: Brigadeiro | B61: =H34 -> 23 | E61: 4 | F61: 0 | G61: =E61-F61 -> 4 | H61: =B61-C61+D61-G61 -> 19 | I61: =G61*6 -> 24
A62: Buriti | B62: =H35 -> 35 | E62: 6 | F62: 4 | G62: =E62-F62 -> 2 | H62: =B62-C62+D62-G62 -> 33 | I62: =G62*6 -> 12
A63: Coco | B63: =H36 -> 30 | E63: 5 | F63: 5 | G63: =E63-F63 -> 0 | H63: =B63-C63+D63-G63 -> 30 | I63: =G63*6 -> 0
A64: Coco Queimado | B64: =H37 -> 17 | C64: 1 | E64: 5 | F64: 3 | G64: =E64-F64 -> 2 | H64: =B64-C64+D64-G64 -> 14 | I64: =G64*6 -> 12
A65: Cupuaçu | B65: =H38 -> 11 | E65: 6 | F65: 3 | G65: =E65-F65 -> 3 | H65: =B65-C65+D65-G65 -> 8 | I65: =G65*6 -> 18
A66: Maracujá | B66: =H39 -> 30 | E66: 6 | F66: 4 | G66: =E66-F66 -> 2 | H66: =B66-C66+D66-G66 -> 28 | I66: =G66*6 -> 12
A67: Maracujá com nutella | B67: =H40 -> 20 | E67: 6 | F67: 2 | G67: =E67-F67 -> 4 | H67: =B67-C67+D67-G67 -> 16 | I67: =G67*6 -> 24
A68: Milho verde | B68: =H41 -> 14 | E68: 2 | F68: 1 | G68: =E68-F68 -> 1 | H68: =B68-C68+D68-G68 -> 13 | I68: =G68*6 -> 6
A69: Morango | B69: =H42 -> 28 | E69: 5 | F69: 4 | G69: =E69-F69 -> 1 | H69: =B69-C69+D69-G69 -> 27 | I69: =G69*6 -> 6
A70: Morango com Nutella | B70: =H43 -> 12 | E70: 6 | F70: 1 | G70: =E70-F70 -> 5 | H70: =B70-C70+D70-G70 -> 7 | I70: =G70*6 -> 30
A71: Mousse de limão | B71: =H44 -> 7 | E71: 4 | F71: 2 | G71: =E71-F71 -> 2 | H71: =B71-C71+D71-G71 -> 5 | I71: =G71*6 -> 12
A72: Ninho com Nutella | B72: =H45 -> 23 | E72: 10 | F72: 0 | G72: =E72-F72 -> 10 | H72: =B72-C72+D72-G72 -> 13 | I72: =G72*6 -> 60
A73: Ninho com Morango | B73: =H46 -> 16 | E73: 6 | F73: 4 | G73: =E73-F73 -> 2 | H73: =B73-C73+D73-G73 -> 14 | I73: =G73*6 -> 12
A74: Oreo | B74: =H47 -> 15 | E74: 4 | F74: 3 | G74: =E74-F74 -> 1 | H74: =B74-C74+D74-G74 -> 14 | I74: =G74*6 -> 6
A75: Prestígio | B75: =H48 -> 37 | E75: 8 | F75: 7 | G75: =E75-F75 -> 1 | H75: =B75-C75+D75-G75 -> 36 | I75: =G75*6 -> 6
A76: Uva | B76: =H49 -> 16 | E76: 2 | F76: 1 | G76: =E76-F76 -> 1 | H76: =B76-C76+D76-G76 -> 15 | I76: =G76*6 -> 6
A77: Zero lactose | B77: =H50 -> 21 | E77: 4 | F77: 2 | G77: =E77-F77 -> 2 | H77: =B77-C77+D77-G77 -> 19 | I77: =G77*6 -> 12
A78: TOTAL | B78: =SUM(B57:B77) -> 441 | E78: =SUM(E56:E77) -> 113 | F78: =SUM(F56:F77) -> 56 | G78: =SUM(G56:G77) -> 57 | H78: =SUM(H57:H77) -> 415 | I78: =SUM(I56:I77) -> 342
F79: Saldo
E80: Valor Total de Venda do dia - GELADINHOS | I80: =SUM(I57:I77) -> 342
B82: Data: 05/02/2026
A83: SABORES | B83: Estoque Inicial | C83: Furou | D83: Fez | E83: Quantidade de Geladinhos | F83: Voltaram | G83: Vendidos | H83: Estoque Final | I83: R$
A84: Abacate | B84: =H57 -> 23 | E84: 6 | F84: 5 | G84: =E84-F84 -> 1 | H84: =B84-C84+D84-G84 -> 22 | I84: =G84*6 -> 6
A85: Abacaxi | B85: =H58 -> 37 | E85: 6 | F85: 2 | G85: =E85-F85 -> 4 | H85: =B85-C85+D85-G85 -> 33 | I85: =G85*6 -> 24
A86: Açaí | B86: =H59 -> 35 | E86: 6 | F86: 5 | G86: =E86-F86 -> 1 | H86: =B86-C86+D86-G86 -> 34 | I86: =G86*6 -> 6
A87: Amendoim | B87: =H60 -> 9 | D87: 29 | E87: 6 | F87: 0 | G87: =E87-F87 -> 6 | H87: =B87-C87+D87-G87 -> 32 | I87: =G87*6 -> 36
A88: Brigadeiro | B88: =H61 -> 19 | E88: 4 | F88: 2 | G88: =E88-F88 -> 2 | H88: =B88-C88+D88-G88 -> 17 | I88: =G88*6 -> 12
A89: Buriti | B89: =H62 -> 33 | E89: 6 | F89: 5 | G89: =E89-F89 -> 1 | H89: =B89-C89+D89-G89 -> 32 | I89: =G89*6 -> 6
A90: Coco | B90: =H63 -> 30 | E90: 5 | F90: 5 | G90: =E90-F90 -> 0 | H90: =B90-C90+D90-G90 -> 30 | I90: =G90*6 -> 0
A91: Coco Queimado | B91: =H64 -> 14 | E91: 4 | F91: 2 | G91: =E91-F91 -> 2 | H91: =B91-C91+D91-G91 -> 12 | I91: =G91*6 -> 12
A92: Cupuaçu | B92: =H65 -> 8 | E92: 6 | F92: 6 | G92: =E92-F92 -> 0 | H92: =B92-C92+D92-G92 -> 8 | I92: =G92*6 -> 0
A93: Maracujá | B93: =H66 -> 28 | E93: 6 | F93: 5 | G93: =E93-F93 -> 1 | H93: =B93-C93+D93-G93 -> 27 | I93: =G93*6 -> 6
A94: Maracujá com nutella | B94: =H67 -> 16 | E94: 6 | F94: 3 | G94: =E94-F94 -> 3 | H94: =B94-C94+D94-G94 -> 13 | I94: =G94*6 -> 18
A95: Milho verde | B95: =H68 -> 13 | E95: 2 | F95: 2 | G95: =E95-F95 -> 0 | H95: =B95-C95+D95-G95 -> 13 | I95: =G95*6 -> 0
A96: Morango | B96: =H69 -> 27 | E96: 5 | F96: 5 | G96: =E96-F96 -> 0 | H96: =B96-C96+D96-G96 -> 27 | I96: =G96*6 -> 0
A97: Morango com Nutella | B97: =H70 -> 7 | D97: 30 | E97: 6 | F97: 3 | G97: =E97-F97 -> 3 | H97: =B97-C97+D97-G97 -> 34 | I97: =G97*6 -> 18
A98: Mousse de limão | B98: =H71 -> 5 | E98: 4 | F98: 3 | G98: =E98-F98 -> 1 | H98: =B98-C98+D98-G98 -> 4 | I98: =G98*6 -> 6
A99: Ninho com Nutella | B99: =H72 -> 13 | D99: 28 | E99: 10 | F99: 6 | G99: =E99-F99 -> 4 | H99: =B99-C99+D99-G99 -> 37 | I99: =G99*6 -> 24
A100: Ninho com Morango | B100: =H73 -> 14 | E100: 6 | F100: 5 | G100: =E100-F100 -> 1 | H100: =B100-C100+D100-G100 -> 13 | I100: =G100*6 -> 6
A101: Oreo | B101: =H74 -> 14 | E101: 4 | F101: 2 | G101: =E101-F101 -> 2 | H101: =B101-C101+D101-G101 -> 12 | I101: =G101*6 -> 12
A102: Prestígio | B102: =H75 -> 36 | E102: 8 | F102: 6 | G102: =E102-F102 -> 2 | H102: =B102-C102+D102-G102 -> 34 | I102: =G102*6 -> 12
A103: Uva | B103: =H76 -> 15 | E103: 2 | F103: 0 | G103: =E103-F103 -> 2 | H103: =B103-C103+D103-G103 -> 13 | I103: =G103*6 -> 12
A104: Zero lactose coco | B104: 23 | E104: 3 | F104: 1 | G104: =E104-F104 -> 2 | H104: =B104-C104+D104-G104 -> 21 | I104: =G104*6 -> 12
A105: Zero lactose morango | B105: =H77 -> 19 | E105: 2 | F105: 2 | G105: =E105-F105 -> 0 | H105: =B105-C105+D105-G105 -> 19 | I105: =G105*6 -> 0
...

Sheet JANEIRO26
B1: Data: 05/01/2026
A2: SABORES | B2: Estoque Inicial | C2: Furou | D2: Fez | E2: Quantidade de Geladinhos | F2: Voltaram | G2: Vendidos | H2: Estoque Final | I2: R$
A3: Abacate | B3: 36 | E3: 6 | F3: 6 | G3: =E3-F3 -> 0 | H3: =B3-C3+D3-G3 -> 36 | I3: =G3*6 -> 0
A4: Abacaxi | B4: 23 | E4: 5 | F4: 3 | G4: =E4-F4 -> 2 | H4: =B4-C4+D4-G4 -> 21 | I4: =G4*6 -> 12
A5: Açaí | B5: 16 | E5: 6 | F5: 6 | G5: =E5-F5 -> 0 | H5: =B5-C5+D5-G5 -> 16 | I5: =G5*6 -> 0
A6: Amendoim | B6: 24 | E6: 7 | F6: 6 | G6: =E6-F6 -> 1 | H6: =B6-C6+D6-G6 -> 23 | I6: =G6*6 -> 6
A7: Brigadeiro | B7: 25 | E7: 4 | F7: 3 | G7: =E7-F7 -> 1 | H7: =B7-C7+D7-G7 -> 24 | I7: =G7*6 -> 6
A8: Buriti | B8: 1 | D8: 34 | E8: 8 | F8: 5 | G8: =E8-F8 -> 3 | H8: =B8-C8+D8-G8 -> 32 | I8: =G8*6 -> 18
A9: Coco | B9: 32 | E9: 5 | F9: 5 | G9: =E9-F9 -> 0 | H9: =B9-C9+D9-G9 -> 32 | I9: =G9*6 -> 0
A10: Coco Queimado | B10: 14 | E10: 4 | F10: 4 | G10: =E10-F10 -> 0 | H10: =B10-C10+D10-G10 -> 14 | I10: =G10*6 -> 0
A11: Cupuaçu | B11: 6 | D11: 30 | E11: 5 | F11: 4 | G11: =E11-F11 -> 1 | H11: =B11-C11+D11-G11 -> 35 | I11: =G11*6 -> 6
A12: Maracujá | B12: 34 | E12: 6 | F12: 5 | G12: =E12-F12 -> 1 | H12: =B12-C12+D12-G12 -> 33 | I12: =G12*6 -> 6
A13: Maracujá com nutella | B13: 29 | E13: 6 | F13: 2 | G13: =E13-F13 -> 4 | H13: =B13-C13+D13-G13 -> 25 | I13: =G14*6 -> 0
A14: Milho verde | B14: 14 | D14: 4 | E14: 2 | F14: 2 | G14: =E14-F14 -> 0 | H14: =B14-C14+D14-G14 -> 18 | I14: =G15*6 -> 0
A15: Morango | B15: 28 | E15: 6 | F15: 6 | G15: =E15-F15 -> 0 | H15: =B15-C15+D15-G15 -> 28 | I15: =G15*6 -> 0
A16: Morango com Nutella | B16: 21 | E16: 6 | F16: 3 | G16: =E16-F16 -> 3 | H16: =B16-C16+D16-G16 -> 18 | I16: =G16*6 -> 18
A17: Mousse de limão | B17: 2 | C17: 1 | D17: 26 | E17: 4 | F17: 4 | G17: =E17-F17 -> 0 | H17: =B17-C17+D17-G17 -> 27 | I17: =G17*6 -> 0
A18: Ninho com Nutella | B18: 20 | E18: 8 | F18: 7 | G18: =E18-F18 -> 1 | H18: =B18-C18+D18-G18 -> 19 | I18: =G18*6 -> 6
A19: Ninho com Morango | B19: 28 | E19: 6 | F19: 5 | G19: =E19-F19 -> 1 | H19: =B19-C19+D19-G19 -> 27 | I19: =G19*6 -> 6
A20: Oreo | B20: 10 | E20: 4 | F20: 4 | G20: =E20-F20 -> 0 | H20: =B20-C20+D20-G20 -> 10 | I20: =G20*6 -> 0
A21: Prestígio | B21: 15 | E21: 8 | F21: 4 | G21: =E21-F21 -> 4 | H21: =B21-C21+D21-G21 -> 11 | I21: =G21*6 -> 24
A22: Uva | B22: 27 | E22: 2 | F22: 2 | G22: =E22-F22 -> 0 | H22: =B22-C22+D22-G22 -> 27 | I22: =G22*6 -> 0
A23: Zero lactose | B23: 14 | D23: 21 | E23: 6 | F23: 6 | G23: =E23-F23 -> 0 | H23: =B23-C23+D23-G23 -> 35 | I23: =G23*6 -> 0
A24: TOTAL | B24: =SUM(B3:B23) -> 419 | E24: =SUM(E2:E23) -> 114 | F24: =SUM(F2:F23) -> 92 | G24: =SUM(G2:G23) -> 22 | H24: =SUM(H3:H23) -> 511 | I24: =SUM(I2:I23) -> 108
F25: Saldo
E26: Valor Total de Venda do dia - GELADINHOS | I26: =SUM(I3:I23) -> 108
B28: Data: 06/01/2026
A29: SABORES | B29: Estoque Inicial | C29: Furou | D29: Fez | E29: Quantidade de Geladinhos | F29: Voltaram | G29: Vendidos | H29: Estoque Final | I29: R$
A30: Abacate | B30: =H3 -> 36 | E30: 6 | F30: 5 | G30: =E30-F30 -> 1 | H30: =B30-C30+D30-G30 -> 35 | I30: =G30*6 -> 6
A31: Abacaxi | B31: =H4 -> 21 | E31: 5 | F31: 3 | G31: =E31-F31 -> 2 | H31: =B31-C31+D31-G31 -> 19 | I31: =G31*6 -> 12
A32: Açaí | B32: =H5 -> 16 | E32: 5 | F32: 5 | G32: =E32-F32 -> 0 | H32: =B32-C32+D32-G32 -> 16 | I32: =G32*6 -> 0
A33: Amendoim | B33: =H6 -> 23 | E33: 6 | F33: 0 | G33: =E33-F33 -> 6 | H33: =B33-C33+D33-G33 -> 17 | I33: =G33*6 -> 36
A34: Brigadeiro | B34: =H7 -> 24 | E34: 4 | F34: 4 | G34: =E34-F34 -> 0 | H34: =B34-C34+D34-G34 -> 24 | I34: =G34*6 -> 0
A35: Buriti | B35: =H8 -> 32 | E35: 6 | F35: 5 | G35: =E35-F35 -> 1 | H35: =B35-C35+D35-G35 -> 31 | I35: =G35*6 -> 6
A36: Coco | B36: =H9 -> 32 | E36: 5 | F36: 5 | G36: =E36-F36 -> 0 | H36: =B36-C36+D36-G36 -> 32 | I36: =G36*6 -> 0
A37: Coco Queimado | B37: =H10 -> 14 | E37: 4 | F37: 3 | G37: =E37-F37 -> 1 | H37: =B37-C37+D37-G37 -> 13 | I37: =G37*6 -> 6
A38: Cupuaçu | B38: =H11 -> 35 | E38: 6 | F38: 6 | G38: =E38-F38 -> 0 | H38: =B38-C38+D38-G38 -> 35 | I38: =G38*6 -> 0
A39: Maracujá | B39: =H12 -> 33 | E39: 6 | F39: 5 | G39: =E39-F39 -> 1 | H39: =B39-C39+D39-G39 -> 32 | I39: =G39*6 -> 6
A40: Maracujá com nutella | B40: =H13 -> 25 | E40: 6 | F40: 3 | G40: =E40-F40 -> 3 | H40: =B40-C40+D40-G40 -> 22 | I40: =G41*6 -> 0
A41: Milho verde | B41: =H14 -> 18 | E41: 2 | F41: 2 | G41: =E41-F41 -> 0 | H41: =B41-C41+D41-G41 -> 18 | I41: =G42*6 -> 6
A42: Morango | B42: =H15 -> 28 | E42: 5 | F42: 4 | G42: =E42-F42 -> 1 | H42: =B42-C42+D42-G42 -> 27 | I42: =G42*6 -> 6
A43: Morango com Nutella | B43: =H16 -> 18 | E43: 6 | F43: 3 | G43: =E43-F43 -> 3 | H43: =B43-C43+D43-G43 -> 15 | I43: =G43*6 -> 18
A44: Mousse de limão | B44: =H17 -> 27 | E44: 4 | F44: 3 | G44: =E44-F44 -> 1 | H44: =B44-C44+D44-G44 -> 26 | I44: =G44*6 -> 6
A45: Ninho com Nutella | B45: =H18 -> 19 | E45: 6 | F45: 1 | G45: =E45-F45 -> 5 | H45: =B45-C45+D45-G45 -> 14 | I45: =G45*6 -> 30
A46: Ninho com Morango | B46: =H19 -> 27 | E46: 6 | F46: 3 | G46: =E46-F46 -> 3 | H46: =B46-C46+D46-G46 -> 24 | I46: =G46*6 -> 18
A47: Oreo | B47: =H20 -> 10 | E47: 4 | F47: 4 | G47: =E47-F47 -> 0 | H47: =B47-C47+D47-G47 -> 10 | I47: =G47*6 -> 0
A48: Prestígio | B48: =H21 -> 11 | D48: 32 | E48: 8 | F48: 4 | G48: =E48-F48 -> 4 | H48: =B48-C48+D48-G48 -> 39 | I48: =G48*6 -> 24
A49: Uva | B49: =H22 -> 27 | E49: 2 | F49: 2 | G49: =E49-F49 -> 0 | H49: =B49-C49+D49-G49 -> 27 | I49: =G49*6 -> 0
A50: Zero lactose | B50: =H23 -> 35 | E50: 6 | F50: 6 | G50: =E50-F50 -> 0 | H50: =B50-C50+D50-G50 -> 35 | I50: =G50*6 -> 0
A51: TOTAL | B51: =SUM(B30:B50) -> 511 | E51: =SUM(E29:E50) -> 108 | F51: =SUM(F29:F50) -> 76 | G51: =SUM(G29:G50) -> 32 | H51: =SUM(H30:H50) -> 511 | I51: =SUM(I29:I50) -> 180
F52: Saldo
E53: Valor Total de Venda do dia - GELADINHOS | I53: =SUM(I30:I50) -> 180
B55: Data: 07/01/2026
A56: SABORES | B56: Estoque Inicial | C56: Furou | D56: Fez | E56: Quantidade de Geladinhos | F56: Voltaram | G56: Vendidos | H56: Estoque Final | I56: R$
A57: Abacate | B57: =H30 -> 35 | E57: 6 | F57: 6 | G57: =E57-F57 -> 0 | H57: =B57-C57+D57-G57 -> 35 | I57: =G57*6 -> 0
A58: Abacaxi | B58: =H31 -> 19 | E58: 5 | F58: 4 | G58: =E58-F58 -> 1 | H58: =B58-C58+D58-G58 -> 18 | I58: =G58*6 -> 6
A59: Açaí | B59: =H32 -> 16 | E59: 5 | F59: 2 | G59: =E59-F59 -> 3 | H59: =B59-C59+D59-G59 -> 13 | I59: =G59*6 -> 18
A60: Amendoim | B60: =H33 -> 17 | E60: 7 | F60: 6 | G60: =E60-F60 -> 1 | H60: =B60-C60+D60-G60 -> 16 | I60: =G60*6 -> 6
A61: Brigadeiro | B61: =H34 -> 24 | E61: 4 | F61: 3 | G61: =E61-F61 -> 1 | H61: =B61-C61+D61-G61 -> 23 | I61: =G61*6 -> 6
A62: Buriti | B62: =H35 -> 31 | E62: 6 | F62: 5 | G62: =E62-F62 -> 1 | H62: =B62-C62+D62-G62 -> 30 | I62: =G62*6 -> 6
A63: Coco | B63: =H36 -> 32 | E63: 5 | F63: 4 | G63: =E63-F63 -> 1 | H63: =B63-C63+D63-G63 -> 31 | I63: =G63*6 -> 6
A64: Coco Queimado | B64: =H37 -> 13 | E64: 4 | F64: 3 | G64: =E64-F64 -> 1 | H64: =B64-C64+D64-G64 -> 12 | I64: =G64*6 -> 6
A65: Cupuaçu | B65: =H38 -> 35 | E65: 6 | F65: 6 | G65: =E65-F65 -> 0 | H65: =B65-C65+D65-G65 -> 35 | I65: =G65*6 -> 0
A66: Maracujá | B66: =H39 -> 32 | E66: 6 | F66: 4 | G66: =E66-F66 -> 2 | H66: =B66-C66+D66-G66 -> 30 | I66: =G66*6 -> 12
A67: Maracujá com nutella | B67: =H40 -> 22 | E67: 6 | F67: 5 | G67: =E67-F67 -> 1 | H67: =B67-C67+D67-G67 -> 21 | I67: =G68*6 -> 6
A68: Milho verde | B68: =H41 -> 18 | E68: 2 | F68: 1 | G68: =E68-F68 -> 1 | H68: =B68-C68+D68-G68 -> 17 | I68: =G69*6 -> 0
A69: Morango | B69: =H42 -> 27 | E69: 6 | F69: 6 | G69: =E69-F69 -> 0 | H69: =B69-C69+D69-G69 -> 27 | I69: =G69*6 -> 0
A70: Morango com Nutella | B70: =H43 -> 15 | E70: 6 | F70: 3 | G70: =E70-F70 -> 3 | H70: =B70-C70+D70-G70 -> 12 | I70: =G70*6 -> 18
A71: Mousse de limão | B71: =H44 -> 26 | E71: 4 | F71: 4 | G71: =E71-F71 -> 0 | H71: =B71-C71+D71-G71 -> 26 | I71: =G71*6 -> 0
A72: Ninho com Nutella | B72: =H45 -> 14 | D72: 27 | E72: 7 | F72: 0 | G72: =E72-F72 -> 7 | H72: =B72-C72+D72-G72 -> 34 | I72: =G72*6 -> 42
A73: Ninho com Morango | B73: =H46 -> 24 | E73: 6 | F73: 5 | G73: =E73-F73 -> 1 | H73: =B73-C73+D73-G73 -> 23 | I73: =G73*6 -> 6
A74: Oreo | B74: =H47 -> 10 | E74: 4 | F74: 1 | G74: =E74-F74 -> 3 | H74: =B74-C74+D74-G74 -> 7 | I74: =G74*6 -> 18
A75: Prestígio | B75: =H48 -> 39 | E75: 8 | F75: 7 | G75: =E75-F75 -> 1 | H75: =B75-C75+D75-G75 -> 38 | I75: =G75*6 -> 6
A76: Uva | B76: =H49 -> 27 | E76: 2 | F76: 2 | G76: =E76-F76 -> 0 | H76: =B76-C76+D76-G76 -> 27 | I76: =G76*6 -> 0
A77: Zero lactose | B77: =H50 -> 35 | E77: 6 | F77: 5 | G77: =E77-F77 -> 1 | H77: =B77-C77+D77-G77 -> 34 | I77: =G77*6 -> 6
A78: TOTAL | B78: =SUM(B57:B77) -> 511 | E78: =SUM(E56:E77) -> 111 | F78: =SUM(F56:F77) -> 82 | G78: =SUM(G56:G77) -> 29 | H78: =SUM(H57:H77) -> 509 | I78: =SUM(I56:I77) -> 168
F79: Saldo
E80: Valor Total de Venda do dia - GELADINHOS | I80: =SUM(I57:I77) -> 168
B82: Data: 08/01/2026
A83: SABORES | B83: Estoque Inicial | C83: Furou | D83: Fez | E83: Quantidade de Geladinhos | F83: Voltaram | G83: Vendidos | H83: Estoque Final | I83: R$
A84: Abacate | B84: =H57 -> 35 | E84: 6 | F84: 3 | G84: =E84-F84 -> 3 | H84: =B84-C84+D84-G84 -> 32 | I84: =G84*6 -> 18
A85: Abacaxi | B85: =H58 -> 18 | E85: 5 | F85: 0 | G85: =E85-F85 -> 5 | H85: =B85-C85+D85-G85 -> 13 | I85: =G85*6 -> 30
A86: Açaí | B86: =H59 -> 13 | E86: 6 | F86: 5 | G86: =E86-F86 -> 1 | H86: =B86-C86+D86-G86 -> 12 | I86: =G86*6 -> 6
A87: Amendoim | B87: =H60 -> 16 | D87: 27 | E87: 7 | F87: 0 | G87: =E87-F87 -> 7 | H87: =B87-C87+D87-G87 -> 36 | I87: =G87*6 -> 42
A88: Brigadeiro | B88: =H61 -> 23 | E88: 4 | F88: 3 | G88: =E88-F88 -> 1 | H88: =B88-C88+D88-G88 -> 22 | I88: =G88*6 -> 6
A89: Buriti | B89: =H62 -> 30 | E89: 6 | F89: 6 | G89: =E89-F89 -> 0 | H89: =B89-C89+D89-G89 -> 30 | I89: =G89*6 -> 0
A90: Coco | B90: =H63 -> 31 | E90: 5 | F90: 4 | G90: =E90-F90 -> 1 | H90: =B90-C90+D90-G90 -> 30 | I90: =G90*6 -> 6
A91: Coco Queimado | B91: =H64 -> 12 | E91: 3 | F91: 0 | G91: =E91-F91 -> 3 | H91: =B91-C91+D91-G91 -> 9 | I91: =G91*6 -> 18
A92: Cupuaçu | B92: =H65 -> 35 | E92: 6 | F92: 4 | G92: =E92-F92 -> 2 | H92: =B92-C92+D92-G92 -> 33 | I92: =G92*6 -> 12
A93: Maracujá | B93: =H66 -> 30 | E93: 6 | F93: 2 | G93: =E93-F93 -> 4 | H93: =B93-C93+D93-G93 -> 26 | I93: =G93*6 -> 24
A94: Maracujá com nutella | B94: =H67 -> 21 | E94: 6 | F94: 5 | G94: =E94-F94 -> 1 | H94: =B94-C94+D94-G94 -> 20 | I94: =G95*6 -> 0
A95: Milho verde | B95: =H68 -> 17 | E95: 2 | F95: 2 | G95: =E95-F95 -> 0 | H95: =B95-C95+D95-G95 -> 17 | I95: =G96*6 -> 6
A96: Morango | B96: =H69 -> 27 | E96: 5 | F96: 4 | G96: =E96-F96 -> 1 | H96: =B96-C96+D96-G96 -> 26 | I96: =G96*6 -> 6
A97: Morango com Nutella | B97: =H70 -> 12 | E97: 6 | F97: 5 | G97: =E97-F97 -> 1 | H97: =B97-C97+D97-G97 -> 11 | I97: =G97*6 -> 6
A98: Mousse de limão | B98: =H71 -> 26 | E98: 4 | F98: 3 | G98: =E98-F98 -> 1 | H98: =B98-C98+D98-G98 -> 25 | I98: =G98*6 -> 6
A99: Ninho com Nutella | B99: =H72 -> 34 | E99: 8 | F99: 7 | G99: =E99-F99 -> 1 | H99: =B99-C99+D99-G99 -> 33 | I99: =G99*6 -> 6
A100: Ninho com Morango | B100: =H73 -> 23 | E100: 6 | F100: 5 | G100: =E100-F100 -> 1 | H100: =B100-C100+D100-G100 -> 22 | I100: =G100*6 -> 6
A101: Oreo | B101: =H74 -> 7 | E101: 4 | F101: 3 | G101: =E101-F101 -> 1 | H101: =B101-C101+D101-G101 -> 6 | I101: =G101*6 -> 6
A102: Prestígio | B102: =H75 -> 38 | E102: 8 | F102: 6 | G102: =E102-F102 -> 2 | H102: =B102-C102+D102-G102 -> 36 | I102: =G102*6 -> 12
A103: Uva | B103: =H76 -> 27 | E103: 2 | F103: 2 | G103: =E103-F103 -> 0 | H103: =B103-C103+D103-G103 -> 27 | I103: =G103*6 -> 0
...

Sheet CONTROLE DE GASTOS
A1: Controle de gastos
A3: Cupuaçu
A4: Ingredientes | B4: Valor produto | C4: Volume | D4: Valor Unit. | E4: Quantidade | G4: UN | H4: Valor
A5: Açúcar | B5: 8 | C5: 2000 | D5: =B5/C5 -> 0.004 | E5: 400 | G5: G | H5: =D5*E5 -> 1.6
A6: Creme de leite | B6: 3 | C6: 1 | D6: =B6/C6 -> 3 | E6: 1 | G6: CX | H6: =D6*E6 -> 3
A7: Embalagem | B7: 35 | C7: 1000 | D7: =B7/C7 -> 0.035 | E7: 20 | G7: un | H7: =D7*E7 -> 0.7
A8: Etiqueta | B8: 120 | C8: 1000 | D8: =B8/C8 -> 0.12 | E8: 20 | G8: UN | H8: =D8*E8 -> 2.4 | J8: Gasto Produção | K8: Geladinho Produzido | L8: Valor Venda | M8: Valor Bruto | N8: Lucro
A9: Leite condensado | B9: 4.5 | C9: 1 | D9: =B9/C9 -> 4.5 | E9: 1 | G9: CX | H9: =D9*E9 -> 4.5 | J9: =H14 -> 30.12 | K9: 20 | L9: 6 | M9: =K9*L9 -> 120 | N9: =M9-J9 -> 89.88
A10: Leite em pó | B10: 38 | C10: 1000 | D10: =B10/C10 -> 0.038 | E10: 60 | G10: G | H10: =D10*E10 -> 2.28
A11: Leite integral | B11: 5 | C11: 1 | D11: =B11/C11 -> 5 | E11: 1.5 | G11: L | H11: =D11*E11 -> 7.5
A12: Liga neutra | B12: 32 | C12: 1000 | D12: =B12/C12 -> 0.032 | E12: 20 | G12: G | H12: =D12*E12 -> 0.64
A13: Polpa | B13: 25 | C13: 1000 | D13: =B13/C13 -> 0.025 | E13: 300 | G13: pc | H13: =D13*E13 -> 7.5
E14: Total | H14: =SUM(H5:H13) -> 30.12
A15: Controle de gastos
A17: Açaí
A18: Açúcar | B18: 8 | C18: 2000 | D18: =B18/C18 -> 0.004 | E18: 500 | G18: G | H18: =D18*E18 -> 2
A19: Creme de leite | B19: 3 | C19: 1 | D19: =B19/C19 -> 3 | E19: 1 | G19: CX | H19: =D19*E19 -> 3
A20: Banana | B20: 6 | C20: 1000 | D20: =B20/C20 -> 0.006 | E20: 96 | G20: g | H20: =D20*E20 -> 0.576
A21: Base - açaí | B21: 40 | C21: 1000 | D21: =B21/C21 -> 0.04 | E21: 75 | G21: g | H21: =D21*E21 -> 3
A22: Embalagem | B22: 35 | C22: 1000 | D22: =B22/C22 -> 0.035 | E22: 30 | G22: un | H22: =D22*E22 -> 1.05
A23: Etiqueta | B23: 120 | C23: 1000 | D23: =B23/C23 -> 0.12 | E23: 30 | G23: UN | H23: =D23*E23 -> 3.6 | J23: Gasto Produção | K23: Geladinho Produzido | L23: Valor Venda | M23: Valor Bruto | N23: Lucro
A24: Leite condensado triângulo | B24: 4.5 | C24: 1 | D24: =B24/C24 -> 4.5 | E24: 2 | G24: CX | H24: =D24*E24 -> 9 | J24: =H29 -> 62.486 | K24: 30 | L24: 6 | M24: =K24*L24 -> 180 | N24: =M24-J24 -> 117.514
A25: Leite em pó | B25: 38 | C25: 1000 | D25: =B25/C25 -> 0.038 | E25: 60 | G25: G | H25: =D25*E25 -> 2.28
A26: Leite integral | B26: 5 | C26: 1 | D26: =B26/C26 -> 5 | E26: 1.5 | G26: L | H26: =D26*E26 -> 7.5
A27: Liga neutra | B27: 32 | C27: 1000 | D27: =B27/C27 -> 0.032 | E27: 15 | G27: G | H27: =D27*E27 -> 0.48
A28: Polpa | B28: 30 | C28: 1000 | D28: =B28/C28 -> 0.03 | E28: 1000 | G28: pc | H28: =D28*E28 -> 30
E29: Total | H29: =SUM(H18:H28) -> 62.486
A31: Controle de gastos
A33: Coco/Coco queimado
A34: Ingredientes | B34: Valor produto | C34: Volume | D34: Valor Unit. | E34: Quantidade | H34: Valor
A35: Açúcar | B35: 8 | C35: 2000 | D35: =B35/C35 -> 0.004 | E35: 450 | G35: G | H35: =D35*E35 -> 1.8
A36: Coco Ralado seco | B36: 45 | C36: 1000 | D36: =B36/C36 -> 0.045 | E36: 100 | G36: G | H36: =D36*E36 -> 4.5
A37: Coco Ralado fresco | B37: 20 | C37: 1000 | D37: =B37/C37 -> 0.02 | E37: 100 | G37: G | H37: =D37*E37 -> 2
A38: Creme de leite | B38: 3 | C38: 1 | D38: =B38/C38 -> 3 | E38: 1 | G38: CX | H38: =D38*E38 -> 3 | J38: Gasto Produção | K38: Geladinho Produzido | L38: Valor Venda | M38: Valor Bruto | N38: Lucro
A39: Embalagem | B39: 35 | C39: 1000 | D39: =B39/C39 -> 0.035 | E39: 25 | G39: un | H39: =D39*E39 -> 0.875
A40: Etiqueta | B40: 120 | C40: 1000 | D40: =B40/C40 -> 0.12 | E40: 25 | G40: UN | H40: =D40*E40 -> 3 | J40: =H46 -> 33.095 | K40: 25 | L40: 6 | M40: 125 | N40: 89.69
A41: Leite condensado | B41: 4.5 | C41: 1 | D41: =B41/C41 -> 4.5 | E41: 1 | G41: CX | H41: =D41*E41 -> 4.5
A42: Leite de coco | B42: 3 | C42: 1 | D42: =B42/C42 -> 3 | E42: 1 | G42: VD | H42: =D42*E42 -> 3
A43: Leite em pó | B43: 38 | C43: 1000 | D43: =B43/C43 -> 0.038 | E43: 60 | G43: G | H43: =D43*E43 -> 2.28
A44: Leite integral | B44: 5 | C44: 1 | D44: =B44/C44 -> 5 | E44: 1.5 | G44: LT | H44: =D44*E44 -> 7.5
A45: Liga neutra | B45: 32 | C45: 1000 | D45: =B45/C45 -> 0.032 | E45: 20 | G45: G | H45: =D45*E45 -> 0.64
E46: Total | H46: =SUM(H35:H45) -> 33.095
A48: Controle de gastos
A50: Morango
A51: Ingredientes | B51: Valor produto | C51: Volume | D51: Valor Unit. | E51: Quantidade | H51: Valor
A52: Açúcar | B52: 8 | C52: 2000 | D52: =B52/C52 -> 0.004 | E52: 300 | G52: G | H52: =D52*E52 -> 1.2
A53: Açúcar geleia | B53: 8 | C53: 2000 | D53: =B53/C53 -> 0.004 | E53: 250 | G53: G | H53: =D53*E53 -> 1
A54: Creme de leite | B54: 3.5 | C54: 1 | D54: =B54/C54 -> 3.5 | E54: 1 | G54: CX | H54: =D54*E54 -> 3.5
A55: Embalagem | B55: 35 | C55: 1000 | D55: =B55/C55 -> 0.035 | E55: 20 | G55: un | H55: =D55*E55 -> 0.7
A56: Etiqueta | B56: 120 | C56: 1000 | D56: =B56/C56 -> 0.12 | E56: 20 | G56: UN | H56: =D56*E56 -> 2.4 | J56: Gasto Produção | K56: Geladinho Produzido | L56: Valor Venda | M56: Valor Bruto | N56: Lucro
A57: Leite condensado | B57: 4.5 | C57: 1 | D57: =B57/C57 -> 4.5 | E57: 1 | G57: CX | H57: =D57*E57 -> 4.5 | J57: =H63 -> 49.22 | K57: 20 | L57: 6 | M57: =K57*L57 -> 120 | N57: =M57-J57 -> 70.78
A58: Leite em pó | B58: 38 | C58: 1000 | D58: =B58/C58 -> 0.038 | E58: 60 | G58: G | H58: =D58*E58 -> 2.28
A59: Leite integral | B59: 5 | C59: 1 | D59: =B59/C59 -> 5 | E59: 1.5 | G59: LT | H59: =D59*E59 -> 7.5
A60: Liga neutra | B60: 32 | C60: 1000 | D60: =B60/C60 -> 0.032 | E60: 20 | G60: G | H60: =D60*E60 -> 0.64
A61: Morango | B61: 15 | C61: 250 | D61: =B61/C61 -> 0.06 | E61: 350 | G61: G | H61: =D61*E61 -> 21
A62: Suco | B62: 1.5 | C62: 1 | D62: =B62/C62 -> 1.5 | E62: 3 | G62: UN | H62: =D62*E62 -> 4.5
E63: Total | H63: =SUM(H52:H62) -> 49.22
A65: Controle de gastos
A67: Amendoim
A68: Ingredientes | B68: Valor produto | C68: Volume | D68: Valor Unit. | E68: Quantidade | G68: Un | H68: Valor
A69: Açúcar | B69: 8 | C69: 2000 | D69: =B69/C69 -> 0.004 | E69: 450 | G69: G | H69: =D69*E69 -> 1.8
A70: Amendoim | B70: 13.99 | C70: 500 | D70: =B70/C70 -> 0.02798 | E70: 200 | G70: G | H70: =D70*E70 -> 5.596
A71: Creme de leite | B71: 3 | C71: 1 | D71: =B71/C71 -> 3 | E71: 1 | G71: CX | H71: =D71*E71 -> 3
A72: Embalagem | B72: 35 | C72: 1000 | D72: =B72/C72 -> 0.035 | E72: 20 | G72: un | H72: =D72*E72 -> 0.7
A73: Etiqueta | B73: 120 | C73: 1000 | D73: =B73/C73 -> 0.12 | E73: 20 | G73: UN | H73: =D73*E73 -> 2.4 | J73: Gasto Produção | K73: Geladinho Produzido | L73: Valor Venda | M73: Valor Bruto | N73: Lucro
A74: Leite condensado | B74: 4.5 | C74: 1 | D74: =B74/C74 -> 4.5 | E74: 1 | G74: CX | H74: =D74*E74 -> 4.5 | J74: =H78 -> 28.236 | K74: 20 | L74: 6 | M74: =K74*L74 -> 120 | N74: =M74-J74 -> 91.764
A75: Leite em pó | B75: 35 | C75: 1000 | D75: =B75/C75 -> 0.035 | E75: 60 | G75: G | H75: =D75*E75 -> 2.1
A76: Leite integral | B76: 5 | C76: 1 | D76: =B76/C76 -> 5 | E76: 1.5 | G76: LT | H76: =D76*E76 -> 7.5
A77: Liga neutra | B77: 32 | C77: 1000 | D77: =B77/C77 -> 0.032 | E77: 20 | G77: G | H77: =D77*E77 -> 0.64
E78: Total | H78: =SUM(H69:H77) -> 28.236
A79: Controle de gastos
A81: Prestígio
A82: Ingredientes | B82: Valor produto | C82: Volume | D82: Valor Unit. | E82: Quantidade | H82: Valor
A83: Açúcar | B83: 8 | C83: 2000 | D83: =B83/C83 -> 0.004 | E83: 470 | G83: G | H83: =D83*E83 -> 1.88
A84: Chocolate/fracionado | B84: 38.19 | C84: 1000 | D84: =B84/C84 -> 0.03819 | E84: 100 | G84: G | H84: =D84*E84 -> 3.819
A85: Coco ralado seco | B85: 45 | C85: 1000 | D85: =B85/C85 -> 0.045 | E85: 100 | G85: G | H85: =D85*E85 -> 4.5 | J85: Gasto Produção | K85: Geladinho Produzido | L85: Valor Venda | M85: Valor Bruto | N85: Lucro
A86: Coco ralado fresco | B86: 20 | C86: 1000 | D86: =B86/C86 -> 0.02 | E86: 100 | G86: G | H86: =D86*E86 -> 2
A87: Creme de leite | B87: 3 | C87: 1 | D87: =B87/C87 -> 3 | E87: 1 | G87: CX | H87: =D87*E87 -> 3 | J87: =H95 -> 36.539 | K87: 20 | L87: 6 | M87: =K87*L87 -> 120 | N87: =M87-J87 -> 83.461
A88: Embalagem | B88: 35 | C88: 1000 | D88: =B88/C88 -> 0.035 | E88: 20 | G88: un | H88: =D88*E88 -> 0.7
A89: Etiqueta | B89: 120 | C89: 1000 | D89: =B89/C89 -> 0.12 | E89: 20 | G89: UN | H89: =D89*E89 -> 2.4
A90: Leite condensado | B90: 4.5 | C90: 1 | D90: =B90/C90 -> 4.5 | E90: 1 | G90: CX | H90: =D90*E90 -> 4.5
A91: Leite de coco | B91: 3.5 | C91: 1 | D91: =B91/C91 -> 3.5 | E91: 1 | G91: VD | H91: =D91*E91 -> 3.5
A92: Leite em pó | B92: 35 | C92: 1000 | D92: =B92/C92 -> 0.035 | E92: 60 | G92: G | H92: =D92*E92 -> 2.1
A93: Leite integral | B93: 5 | C93: 1 | D93: =B93/C93 -> 5 | E93: 1.5 | G93: LT | H93: =D93*E93 -> 7.5
A94: Liga neutra | B94: 32 | C94: 1000 | D94: =B94/C94 -> 0.032 | E94: 20 | G94: G | H94: =D94*E94 -> 0.64
E95: Total | H95: =SUM(H83:H94) -> 36.539
A97: Controle de gastos
A99: Brigadeiro
A100: Ingredientes | B100: Valor produto | C100: Volume | D100: Valor Unit. | E100: Quantidade | H100: Valor
A101: Açúcar | B101: 8 | C101: 2000 | D101: =B101/C101 -> 0.004 | E101: 250 | G101: G | H101: =D101*E101 -> 1
A102: Cobertura Chocolate | B102: 23 | C102: 1000 | D102: =B102/C102 -> 0.023 | E102: 200 | G102: G | H102: =D102*E102 -> 4.6
A103: Chocolate em pó | B103: 35 | C103: 1000 | D103: =B103/C103 -> 0.035 | E103: 180 | G103: G | H103: =D103*E103 -> 6.3 | J103: Gasto Produção | K103: Geladinho Produzido | L103: Valor Venda | M103: Valor Bruto | N103: Lucro
A104: Creme de leite | B104: 3 | C104: 1 | D104: =B104/C104 -> 3 | E104: 1 | G104: CX | H104: =D104*E104 -> 3 | J104: =H113 -> 34.628 | K104: 20 | L104: 6 | M104: =K104*L104 -> 120 | N104: =M104-J104 -> 85.372
A105: Embalagem | B105: 35 | C105: 1000 | D105: =B105/C105 -> 0.035 | E105: 20 | G105: un | H105: =D105*E105 -> 0.7
A106: Etiqueta | B106: 120 | C106: 1000 | D106: =B106/C106 -> 0.12 | E106: 20 | G106: UN | H106: =D106*E106 -> 2.4
A107: Granulado | B107: 23 | C107: 1000 | D107: =B107/C107 -> 0.023 | E107: 6 | G107: G | H107: =D107*E107 -> 0.138
A108: Leite condensado | B108: 4.5 | C108: 1 | D108: =B108/C108 -> 4.5 | E108: 1 | G108: CX | H108: =D108*E108 -> 4.5
A109: Leite em pó | B109: 35 | C109: 1000 | D109: =B109/C109 -> 0.035 | E109: 60 | G109: G | H109: =D109*E109 -> 2.1
A110: Leite integral | B110: 5 | C110: 1 | D110: =B110/C110 -> 5 | E110: 1.5 | G110: LT | H110: =D110*E110 -> 7.5
A111: Liga neutra | B111: 32 | C111: 1000 | D111: =B111/C111 -> 0.032 | E111: 20 | G111: G | H111: =D111*E111 -> 0.64
...
